{"city": ["Mumbai"], "yom": ["2002"], "url": ["http://www.gaadi.com/usedcars/details-824239-Hyundai_Accent_GLX"], "price": ["Rs. 1,11,000"], "transm": ["Petrol"], "kms": ["1,09,000 km "], "fuel": ["Petrol"], "owner": [], "model": ["Hyundai Accent GLX"], "color": ["White"]}
{"city": ["Aurangabad"], "yom": ["2010"], "url": ["http://www.gaadi.com/usedcars/details-824238-Chevrolet_Cruze_LT"], "price": ["Rs. 8,25,000"], "transm": ["Diesel"], "kms": ["68,000 km "], "fuel": ["Diesel"], "owner": [], "model": ["Chevrolet Cruze LT"], "color": ["Summit white"]}
{"city": ["Indore"], "yom": ["2005"], "url": ["http://www.gaadi.com/usedcars/details-824962-Maruti_WagonR_Lx"], "price": ["Rs. 1,50,000"], "transm": ["Petrol"], "kms": ["60,000 km "], "fuel": ["Petrol"], "owner": [], "model": ["Maruti WagonR Lx"], "color": ["Silky silver"]}
{"city": ["Chennai"], "yom": ["2011"], "url": ["http://www.gaadi.com/usedcars/details-825573-Maruti_Swift+DZire_VDi"], "price": ["Rs. 4,50,000"], "transm": ["Diesel"], "kms": ["53,000 km "], "fuel": ["Diesel"], "owner": [], "model": ["Maruti Swift DZire VDi"], "color": ["White"]}
{"city": ["Hyderabad"], "yom": ["2012"], "url": ["http://www.gaadi.com/usedcars/details-825571-Ford_Figo_1.4+Duratorq+ZXI"], "price": ["Rs. 5,00,000"], "transm": ["Diesel"], "kms": ["52,500 km "], "fuel": ["Diesel"], "owner": [], "model": ["Ford Figo 1.4 Duratorq ZXI"], "color": ["Blue"]}
{"city": ["Aurangabad"], "yom": ["2011"], "url": ["http://www.gaadi.com/usedcars/details-824595-Chevrolet_Tavera+Neo_LS+B3++7+seats+BSII"], "price": ["Rs. 7,10,000"], "transm": ["Diesel"], "kms": ["79,000 km "], "fuel": ["Diesel"], "owner": [], "model": ["Chevrolet Tavera Neo LS B3  7 seats BSII"], "color": ["White"]}
{"city": ["Cuttack"], "yom": ["2010"], "url": ["http://www.gaadi.com/usedcars/details-824593-Maruti_WagonR_Vxi"], "price": ["Rs. 2,80,000"], "transm": ["Petrol"], "kms": ["55,000 km "], "fuel": ["Petrol"], "owner": [], "model": ["Maruti WagonR Vxi"], "color": ["Silver"]}
{"city": ["Kolkata"], "yom": ["2011"], "url": ["http://www.gaadi.com/usedcars/details-823899-Tata_Manza_Aura+Quadrajet"], "price": ["Rs. 2,40,000"], "transm": ["Diesel"], "kms": ["82,500 km "], "fuel": ["Diesel"], "owner": [], "model": ["Tata Manza Aura Quadrajet"], "color": ["Blue"]}
{"city": ["Kottayam"], "yom": ["2009"], "url": ["http://www.gaadi.com/usedcars/details-823890-Fiat_Punto_1.3+Emotion"], "price": ["Rs. 2,70,000"], "transm": ["Diesel"], "kms": ["72,500 km "], "fuel": ["Diesel"], "owner": [], "model": ["Fiat Punto 1.3 Emotion"], "color": ["Silver"]}
{"city": ["Aurangabad"], "yom": ["2010"], "url": ["http://www.gaadi.com/usedcars/details-824397-Hyundai_i20_Magna+1.2+Petrol"], "price": ["Rs. 4,80,000"], "transm": ["Petrol"], "kms": ["61,000 km "], "fuel": ["Petrol"], "owner": [], "model": ["Hyundai i20 Magna 1.2 Petrol"], "color": ["White"]}
{"city": ["Kolkata"], "yom": ["2010"], "url": ["http://www.gaadi.com/usedcars/details-824396-Hyundai_Santro+Xing_GLS+LPG"], "price": ["Rs. 2,35,000"], "transm": ["Lpg"], "kms": ["27,108 km "], "fuel": ["Lpg"], "owner": [], "model": ["Hyundai Santro Xing GLS LPG"], "color": ["Maharajah red"]}
{"city": ["New Delhi"], "yom": ["2014"], "url": ["http://www.gaadi.com/usedcars/details-823828-Volkswagen_Vento_1.2+TSI+Comfortline+AT"], "price": ["Rs. 6,59,899"], "transm": ["Petrol"], "kms": ["55,600 km "], "fuel": ["Petrol"], "owner": [], "model": ["Volkswagen Vento 1.2 TSI Comfortline AT"], "color": ["White"]}
{"city": ["Ahmedabad"], "yom": ["2012"], "url": ["http://www.gaadi.com/usedcars/details-823815-Toyota_Fortuner+2009++++2012_4WD+MT"], "price": ["Rs. 18,75,000"], "transm": ["Diesel"], "kms": ["91,618 km "], "fuel": ["Diesel"], "owner": [], "model": ["Toyota Fortuner 2009 -  2012 4WD MT"], "color": ["White"]}
{"city": ["New Delhi"], "yom": ["2011"], "url": ["http://www.gaadi.com/usedcars/details-823765-Maruti_Alto_LXi"], "price": ["Rs. 1,90,000"], "transm": ["Petrol"], "kms": ["55,000 km "], "fuel": ["Petrol"], "owner": [], "model": ["Maruti Alto LXi"], "color": ["Silver"]}
{"city": ["Mumbai"], "yom": ["2005"], "url": ["http://www.gaadi.com/usedcars/details-823762-Hyundai_Santro+Xing_XP"], "price": ["Rs. 1,10,000"], "transm": ["Petrol"], "kms": ["46,590 km "], "fuel": ["Petrol"], "owner": [], "model": ["Hyundai Santro Xing XP"], "color": ["Black"]}
{"city": ["Mumbai"], "yom": ["1997"], "url": ["http://www.gaadi.com/usedcars/details-824297-Maruti_800_AC"], "price": ["Rs. 40,000"], "transm": ["Petrol"], "kms": ["31,415 km "], "fuel": ["Petrol"], "owner": [], "model": ["Maruti 800 AC"], "color": ["Superior white"]}
{"city": ["Mumbai"], "yom": ["2005"], "url": ["http://www.gaadi.com/usedcars/details-824296-Tata_Indigo_GLX"], "price": ["Rs. 75,000"], "transm": ["Petrol"], "kms": ["5,500 km "], "fuel": ["Petrol"], "owner": [], "model": ["Tata Indigo GLX"], "color": ["Mint white"]}
{"city": ["Gurgaon"], "yom": ["2012"], "url": ["http://www.gaadi.com/usedcars/details-824069-Volkswagen_Polo+2010+2014_1.2L+Trendline++Diesel+"], "price": ["Rs. 4,00,000"], "transm": ["Diesel"], "kms": ["50,000 km "], "fuel": ["Diesel"], "owner": [], "model": ["Volkswagen Polo 2010-2014 1.2L Trendline (Diesel)"], "color": ["White"]}
{"city": ["Karnal"], "yom": ["2011"], "url": ["http://www.gaadi.com/usedcars/details-824068-Maruti_Swift+DZire_VDi"], "price": ["Rs. 4,25,000"], "transm": ["Diesel"], "kms": ["1,10,000 km "], "fuel": ["Diesel"], "owner": [], "model": ["Maruti Swift DZire VDi"], "color": ["White"]}
{"city": ["Aurangabad"], "yom": ["2008"], "url": ["http://www.gaadi.com/usedcars/details-824237-Ford_Fiesta+Classic_1.4+ZXi+TDCi"], "price": ["Rs. 3,40,000"], "transm": ["Diesel"], "kms": ["95,000 km "], "fuel": ["Diesel"], "owner": [], "model": ["Ford Fiesta Classic 1.4 ZXi TDCi"], "color": ["Diamond white"]}
{"city": ["Ahmedabad"], "yom": ["2011"], "url": ["http://www.gaadi.com/usedcars/details-824236-Maruti_Alto_LXi+CNG"], "price": ["Rs. 2,25,000"], "transm": ["Cng"], "kms": ["45,000 km "], "fuel": ["Cng"], "owner": [], "model": ["Maruti Alto LXi CNG"], "color": ["White"]}
{"city": ["New Delhi"], "yom": ["2011"], "url": ["http://www.gaadi.com/usedcars/details-824958-Volkswagen_Vento+2010+2014_Comfortline+Petrol"], "price": ["Rs. 4,30,000"], "transm": ["Petrol"], "kms": ["38,000 km "], "fuel": ["Petrol"], "owner": [], "model": ["Volkswagen Vento 2010-2014 Comfortline Petrol"], "color": ["Reflex silver"]}
{"city": ["Indore"], "yom": ["1996"], "url": ["http://www.gaadi.com/usedcars/details-824957-Mahindra_Jeep_Commander+650+DI"], "price": ["Rs. 1,50,000"], "transm": ["Diesel"], "kms": ["70,000 km "], "fuel": ["Diesel"], "owner": [], "model": ["Mahindra Jeep Commander 650 DI"], "color": ["Bright green"]}
{"city": ["New Delhi"], "yom": ["2014"], "url": ["http://www.gaadi.com/usedcars/details-823730-Toyota_Fortuner_2WD+AT"], "price": ["Rs. 23,75,000"], "transm": ["Diesel"], "kms": ["25,000 km "], "fuel": ["Diesel"], "owner": [], "model": ["Toyota Fortuner 2WD AT"], "color": ["Super white"]}
{"city": ["Patiala"], "yom": ["2012"], "url": ["http://www.gaadi.com/usedcars/details-825570-Chevrolet_Cruze_LTZ"], "price": ["Rs. 5,00,000"], "transm": ["Diesel"], "kms": ["50,000 km "], "fuel": ["Diesel"], "owner": [], "model": ["Chevrolet Cruze LTZ"], "color": ["Summit white"]}
{"city": ["New Delhi"], "yom": ["2008"], "url": ["http://www.gaadi.com/usedcars/details-825567-Hyundai_Accent_CNG"], "price": ["Rs. 1,75,000"], "transm": ["Cng"], "kms": ["87,500 km "], "fuel": ["Cng"], "owner": [], "model": ["Hyundai Accent CNG"], "color": ["White"]}
{"city": ["Nagpur"], "yom": ["2013"], "url": ["http://www.gaadi.com/usedcars/details-824592-Maruti_Alto+800_VXi"], "price": ["Rs. 3,00,000"], "transm": ["Petrol"], "kms": ["36,500 km "], "fuel": ["Petrol"], "owner": [], "model": ["Maruti Alto 800 VXi"], "color": ["Superior white"]}
{"city": ["Lucknow"], "yom": ["2012"], "url": ["http://www.gaadi.com/usedcars/details-824588-Honda_City+2008+2013_S+AT"], "price": ["Rs. 6,50,000"], "transm": ["Petrol"], "kms": ["16,000 km "], "fuel": ["Petrol"], "owner": [], "model": ["Honda City 2008-2013 S AT"], "color": ["Sparkling brown metallic"]}
{"city": ["Hyderabad"], "yom": ["1996"], "url": ["http://www.gaadi.com/usedcars/details-823885-Mahindra_Jeep_CJ+500+D"], "price": ["Rs. 2,75,000"], "transm": ["Diesel"], "kms": ["7,500 km "], "fuel": ["Diesel"], "owner": [], "model": ["Mahindra Jeep CJ 500 D"], "color": ["Other"]}
{"city": ["Mumbai"], "yom": ["2010"], "url": ["http://www.gaadi.com/usedcars/details-823880-Chevrolet_Beat_LS"], "price": ["Rs. 2,00,000"], "transm": ["Petrol"], "kms": ["42,146 km "], "fuel": ["Petrol"], "owner": [], "model": ["Chevrolet Beat LS"], "color": ["Green cocktail"]}
{"city": ["Nasik"], "yom": ["2014"], "url": ["http://www.gaadi.com/usedcars/details-824395-Honda_Brio_VX+AT"], "price": ["Rs. 6,10,000"], "transm": ["Petrol"], "kms": ["5,000 km "], "fuel": ["Petrol"], "owner": [], "model": ["Honda Brio VX AT"], "color": ["Red"]}
{"city": ["Trivandram"], "yom": ["2012"], "url": ["http://www.gaadi.com/usedcars/details-824394-Volkswagen_Vento_1.5+TDI+Highline"], "price": ["Rs. 8,70,000"], "transm": ["Diesel"], "kms": ["47,000 km "], "fuel": ["Diesel"], "owner": [], "model": ["Volkswagen Vento 1.5 TDI Highline"], "color": ["Blue"]}
{"city": ["Panaji"], "yom": ["1999"], "url": ["http://www.gaadi.com/usedcars/details-823814-Maruti_Omni_5+Seater"], "price": ["Rs. 1,10,000"], "transm": ["Petrol"], "kms": ["52,500 km "], "fuel": ["Petrol"], "owner": [], "model": ["Maruti Omni 5 Seater"], "color": ["Silver"]}
{"city": ["Hyderabad"], "yom": ["2008"], "url": ["http://www.gaadi.com/usedcars/details-823812-Porsche_Cayman_S"], "price": ["Rs. 48,00,000"], "transm": ["Petrol"], "kms": ["18,000 km "], "fuel": ["Petrol"], "owner": [], "model": ["Porsche Cayman S"], "color": ["Agate grey metalic"]}
{"city": ["Mumbai"], "yom": ["2008"], "url": ["http://www.gaadi.com/usedcars/details-823761-Maruti_Swift+DZire_LDi"], "price": ["Rs. 3,15,000"], "transm": ["Diesel"], "kms": ["1,44,925 km "], "fuel": ["Diesel"], "owner": [], "model": ["Maruti Swift DZire LDi"], "color": ["Silver"]}
{"city": ["Bangalore"], "yom": ["2012"], "url": ["http://www.gaadi.com/usedcars/details-823758-Volkswagen_Polo_1.5+Comfortline"], "price": ["Rs. 5,25,000"], "transm": ["Diesel"], "kms": ["61,809 km "], "fuel": ["Diesel"], "owner": [], "model": ["Volkswagen Polo 1.5 Comfortline"], "color": ["Flash red - volkswagen polo"]}
{"city": ["Bangalore"], "yom": ["2007"], "url": ["http://www.gaadi.com/usedcars/details-824295-Toyota_Innova_G+7+Seater"], "price": ["Rs. 8,00,000"], "transm": ["Diesel"], "kms": ["1,23,216 km "], "fuel": ["Diesel"], "owner": [], "model": ["Toyota Innova G 7-Seater"], "color": ["L green"]}
{"city": ["Patna"], "yom": ["2011"], "url": ["http://www.gaadi.com/usedcars/details-824293-Maruti_Alto_LXi"], "price": ["Rs. 1,90,000"], "transm": ["Petrol"], "kms": ["24,500 km "], "fuel": ["Petrol"], "owner": [], "model": ["Maruti Alto LXi"], "color": ["Red"]}
{"city": ["Karnal"], "yom": ["2009"], "url": ["http://www.gaadi.com/usedcars/details-824067-Maruti_Swift_VDi"], "price": ["Rs. 3,15,000"], "transm": ["Diesel"], "kms": ["55,000 km "], "fuel": ["Diesel"], "owner": [], "model": ["Maruti Swift VDi"], "color": ["Pearl arctict white"]}
{"city": ["Chennai"], "yom": ["2013"], "url": ["http://www.gaadi.com/usedcars/details-824065-Chevrolet_Beat+2010+++2014_1.2+LS"], "price": ["Rs. 5,00,000"], "transm": ["Petrol"], "kms": ["15,000 km "], "fuel": ["Petrol"], "owner": [], "model": ["Chevrolet Beat 2010 - 2014 1.2 LS"], "color": ["Golden"]}
{"city": ["Ahmedabad"], "yom": ["2010"], "url": ["http://www.gaadi.com/usedcars/details-824235-Toyota_Fortuner_4X4+MT"], "price": ["Rs. 14,00,000"], "transm": ["Diesel"], "kms": ["61,000 km "], "fuel": ["Diesel"], "owner": [], "model": ["Toyota Fortuner 4X4 MT"], "color": ["White"]}
{"city": ["Chennai"], "yom": ["2004"], "url": ["http://www.gaadi.com/usedcars/details-824234-Hyundai_Santro+Xing_XG"], "price": ["Rs. 1,60,000"], "transm": ["Petrol"], "kms": ["46,010 km "], "fuel": ["Petrol"], "owner": [], "model": ["Hyundai Santro Xing XG"], "color": ["Silver"]}
{"city": ["Indore"], "yom": ["2002"], "url": ["http://www.gaadi.com/usedcars/details-824956-Mahindra_Jeep_Commander+650+DI"], "price": ["Rs. 2,50,000"], "transm": ["Diesel"], "kms": ["60,000 km "], "fuel": ["Diesel"], "owner": [], "model": ["Mahindra Jeep Commander 650 DI"], "color": ["Bright green"]}
{"city": ["Indore"], "yom": ["2011"], "url": ["http://www.gaadi.com/usedcars/details-824955-Maruti_Eeco_5+Str"], "price": ["Rs. 2,60,000"], "transm": ["Petrol"], "kms": ["45,000 km "], "fuel": ["Petrol"], "owner": [], "model": ["Maruti Eeco 5 Str"], "color": ["White"]}
{"city": ["Bhopal"], "yom": ["2013"], "url": ["http://www.gaadi.com/usedcars/details-823729-Mahindra_Scorpio_S6"], "price": ["Rs. 7,50,000"], "transm": ["Diesel"], "kms": ["38,000 km "], "fuel": ["Diesel"], "owner": [], "model": ["Mahindra Scorpio S6"], "color": ["Diamond white"]}
{"city": ["Bhopal"], "yom": ["2007"], "url": ["http://www.gaadi.com/usedcars/details-823728-Maruti_Swift_LXi"], "price": ["Rs. 2,30,000"], "transm": ["Petrol"], "kms": ["62,000 km "], "fuel": ["Petrol"], "owner": [], "model": ["Maruti Swift LXi"], "color": ["Black"]}
{"city": ["Ankleshwar"], "yom": ["2008"], "url": ["http://www.gaadi.com/usedcars/details-825566-Tata_Safari_4X2+VX+DiCOR+2.2+V+T+T"], "price": ["Rs. 4,30,000"], "transm": ["Diesel"], "kms": ["1,50,000 km "], "fuel": ["Diesel"], "owner": [], "model": ["Tata Safari 4X2 VX DiCOR 2.2 V T T"], "color": ["Silver"]}
{"city": ["Mumbai"], "yom": ["2009"], "url": ["http://www.gaadi.com/usedcars/details-825565-Ford_Ikon_1.4+DuraTorq+TDCi"], "price": ["Rs. 2,25,000"], "transm": ["Diesel"], "kms": ["54,394 km "], "fuel": ["Diesel"], "owner": [], "model": ["Ford Ikon 1.4 DuraTorq TDCi"], "color": ["Paprika red"]}
{"city": ["Jaipur"], "yom": ["2006"], "url": ["http://www.gaadi.com/usedcars/details-823867-Hyundai_Getz_GLE"], "price": ["Rs. 2,00,000"], "transm": ["Petrol"], "kms": ["55,915 km "], "fuel": ["Petrol"], "owner": [], "model": ["Hyundai Getz GLE"], "color": ["Dark red"]}
{"city": ["Gurgaon"], "yom": ["2013"], "url": ["http://www.gaadi.com/usedcars/details-823862-Hyundai_Santro+Xing_GLS"], "price": ["Rs. 2,85,000"], "transm": ["Petrol"], "kms": ["16,344 km "], "fuel": ["Petrol"], "owner": [], "model": ["Hyundai Santro Xing GLS"], "color": ["Coral white"]}
{"city": ["Amritsar"], "yom": ["2011"], "url": ["http://www.gaadi.com/usedcars/details-824393-Skoda_Fabia_Elegance+1.4+PD+TDI"], "price": ["Rs. 4,50,000"], "transm": ["Diesel"], "kms": ["40,000 km "], "fuel": ["Diesel"], "owner": [], "model": ["Skoda Fabia Elegance 1.4 PD TDI"], "color": ["Black magic"]}
{"city": ["Amritsar"], "yom": ["2014"], "url": ["http://www.gaadi.com/usedcars/details-824392-Mahindra_Scorpio_S10"], "price": ["Rs. 9,00,000"], "transm": ["Diesel"], "kms": ["10,000 km "], "fuel": ["Diesel"], "owner": [], "model": ["Mahindra Scorpio S10"], "color": ["Mist silver"]}
{"city": ["New Delhi"], "yom": ["2009"], "url": ["http://www.gaadi.com/usedcars/details-823809-Toyota_Corolla+Altis_1.8+G+MT"], "price": ["Rs. 5,00,000"], "transm": ["Petrol"], "kms": ["65,824 km "], "fuel": ["Petrol"], "owner": [], "model": ["Toyota Corolla Altis 1.8 G MT"], "color": ["White pearl crystal shine"]}
{"city": ["New Delhi"], "yom": ["2008"], "url": ["http://www.gaadi.com/usedcars/details-823808-Tata_Safari_4X2+EX+DiCOR+BS+III"], "price": ["Rs. 4,50,000"], "transm": ["Diesel"], "kms": ["85,193 km "], "fuel": ["Diesel"], "owner": [], "model": ["Tata Safari 4X2 EX DiCOR BS-III"], "color": ["Black"]}
{"city": ["Mumbai"], "yom": ["2000"], "url": ["http://www.gaadi.com/usedcars/details-823757-Hyundai_Santro+Xing_GLS"], "price": ["Rs. 63,000"], "transm": ["Petrol"], "kms": ["1,36,301 km "], "fuel": ["Petrol"], "owner": [], "model": ["Hyundai Santro Xing GLS"], "color": ["Gold"]}
{"city": ["Mumbai"], "yom": ["2004"], "url": ["http://www.gaadi.com/usedcars/details-823756-Hyundai_Accent_GVS"], "price": ["Rs. 1,05,000"], "transm": ["Petrol"], "kms": ["82,621 km "], "fuel": ["Petrol"], "owner": [], "model": ["Hyundai Accent GVS"], "color": ["Black"]}
{"city": ["Mumbai"], "yom": ["2002"], "url": ["http://www.gaadi.com/usedcars/details-824292-Tata_Indica_dls"], "price": ["Rs. 65,000"], "transm": ["Diesel"], "kms": ["1,39,895 km "], "fuel": ["Diesel"], "owner": [], "model": ["Tata Indica dls"], "color": ["Blue"]}
{"city": ["Mumbai"], "yom": ["2009"], "url": ["http://www.gaadi.com/usedcars/details-824291-Tata_Indica_dls"], "price": ["Rs. 1,48,000"], "transm": ["Diesel"], "kms": ["36,000 km "], "fuel": ["Diesel"], "owner": [], "model": ["Tata Indica dls"], "color": ["Dark red"]}
{"city": ["Mumbai"], "yom": ["2009"], "url": ["http://www.gaadi.com/usedcars/details-824064-Tata_Indica+Vista+2008+++2011_Aqua+1.2+Safire"], "price": ["Rs. 2,05,000"], "transm": ["Petrol"], "kms": ["92,000 km "], "fuel": ["Petrol"], "owner": [], "model": ["Tata Indica Vista 2008 - 2011 Aqua 1.2 Safire"], "color": ["Grey"]}
{"city": ["Mumbai"], "yom": ["2011"], "url": ["http://www.gaadi.com/usedcars/details-824063-Tata_Indica+V2_LX"], "price": ["Rs. 1,58,000"], "transm": ["Diesel"], "kms": ["37,000 km "], "fuel": ["Diesel"], "owner": [], "model": ["Tata Indica V2 LX"], "color": ["Burgundy"]}
{"city": ["Amritsar"], "yom": ["2000"], "url": ["http://www.gaadi.com/usedcars/details-824233-Fiat_Palio_1.2+ELX"], "price": ["Rs. 1,50,000"], "transm": ["Petrol"], "kms": ["1,00,000 km "], "fuel": ["Petrol"], "owner": [], "model": ["Fiat Palio 1.2 ELX"], "color": ["Dark blue"]}
{"city": ["Kolkata"], "yom": ["2013"], "url": ["http://www.gaadi.com/usedcars/details-824232-Honda_Amaze_VX+MT+Diesel"], "price": ["Rs. 5,70,000"], "transm": ["Diesel"], "kms": ["32,000 km "], "fuel": ["Diesel"], "owner": [], "model": ["Honda Amaze VX MT Diesel"], "color": ["Crystal black pearl"]}
{"city": ["Vellore"], "yom": ["2011"], "url": ["http://www.gaadi.com/usedcars/details-824953-Ford_Figo_1.4+Duratorq+EXI"], "price": ["Rs. 3,25,000"], "transm": ["Diesel"], "kms": ["82,000 km "], "fuel": ["Diesel"], "owner": [], "model": ["Ford Figo 1.4 Duratorq EXI"], "color": ["Moondust silver"]}
{"city": ["Vellore"], "yom": ["2008"], "url": ["http://www.gaadi.com/usedcars/details-824952-Volkswagen_Passat_Highline+DSG+S++Spl.+Edition+"], "price": ["Rs. 8,50,000"], "transm": ["Diesel"], "kms": ["80,000 km "], "fuel": ["Diesel"], "owner": [], "model": ["Volkswagen Passat Highline DSG S (Spl. Edition)"], "color": ["Candy white"]}
{"city": ["Kolkata"], "yom": ["2011"], "url": ["http://www.gaadi.com/usedcars/details-823725-Honda_Jazz+2011+2013_S"], "price": ["Rs. 3,50,000"], "transm": ["Petrol"], "kms": ["30,000 km "], "fuel": ["Petrol"], "owner": [], "model": ["Honda Jazz 2011-2013 S"], "color": ["White"]}
{"city": ["Kolkata"], "yom": ["2009"], "url": ["http://www.gaadi.com/usedcars/details-823724-Hyundai_i10_Sportz+1.2"], "price": ["Rs. 2,40,000"], "transm": ["Petrol"], "kms": ["37,200 km "], "fuel": ["Petrol"], "owner": [], "model": ["Hyundai i10 Sportz 1.2"], "color": ["Dark red"]}
{"city": ["Ahmedabad"], "yom": ["2010"], "url": ["http://www.gaadi.com/usedcars/details-823861-Mahindra_Scorpio+2010+2014_VLX+2.2+Mhawk+BS+III"], "price": ["Rs. 6,80,000"], "transm": ["Diesel"], "kms": ["1,14,225 km "], "fuel": ["Diesel"], "owner": [], "model": ["Mahindra Scorpio 2010-2014 VLX 2.2 Mhawk BS-III"], "color": ["White"]}
{"city": ["Ahmedabad"], "yom": ["2008"], "url": ["http://www.gaadi.com/usedcars/details-823860-Maruti_WagonR_Vxi"], "price": ["Rs. 2,70,000"], "transm": ["Cng"], "kms": ["50,640 km "], "fuel": ["Cng"], "owner": [], "model": ["Maruti WagonR Vxi"], "color": ["Superior white"]}
{"city": ["Aurangabad"], "yom": ["2011"], "url": ["http://www.gaadi.com/usedcars/details-824391-Maruti_SX4_ZDI"], "price": ["Rs. 6,10,000"], "transm": ["Diesel"], "kms": ["60,000 km "], "fuel": ["Diesel"], "owner": [], "model": ["Maruti SX4 ZDI"], "color": ["Pearl arctict white"]}
{"city": ["Aurangabad"], "yom": ["2012"], "url": ["http://www.gaadi.com/usedcars/details-824390-Maruti_Swift_ZDi"], "price": ["Rs. 5,50,000"], "transm": ["Diesel"], "kms": ["55,000 km "], "fuel": ["Diesel"], "owner": [], "model": ["Maruti Swift ZDi"], "color": ["Pearl arctict white"]}
{"city": ["Hyderabad"], "yom": ["2010"], "url": ["http://www.gaadi.com/usedcars/details-823807-Chevrolet_Optra+Magnum_1.6+LS+Petrol"], "price": ["Rs. 5,00,000"], "transm": ["Petrol"], "kms": ["7,500 km "], "fuel": ["Petrol"], "owner": [], "model": ["Chevrolet Optra Magnum 1.6 LS Petrol"], "color": ["White"]}
{"city": ["Bangalore"], "yom": ["2008"], "url": ["http://www.gaadi.com/usedcars/details-823804-Fiat_Linea+2008+2012_Emotion++Diesel+"], "price": ["Rs. 3,75,000"], "transm": ["Diesel"], "kms": ["52,952 km "], "fuel": ["Diesel"], "owner": [], "model": ["Fiat Linea 2008-2012 Emotion (Diesel)"], "color": ["Burgundy"]}
{"city": ["Mumbai"], "yom": ["2004"], "url": ["http://www.gaadi.com/usedcars/details-823755-Hyundai_Santro+Xing_XS"], "price": ["Rs. 1,10,000"], "transm": ["Petrol"], "kms": ["45,869 km "], "fuel": ["Petrol"], "owner": [], "model": ["Hyundai Santro Xing XS"], "color": ["Fariy leaf"]}
{"city": ["Mumbai"], "yom": ["2005"], "url": ["http://www.gaadi.com/usedcars/details-823753-Toyota_Qualis_GST+Super"], "price": ["Rs. 3,10,000"], "transm": ["Diesel"], "kms": ["80,000 km "], "fuel": ["Diesel"], "owner": [], "model": ["Toyota Qualis GST Super"], "color": ["Silver"]}
{"city": ["Mumbai"], "yom": ["2007"], "url": ["http://www.gaadi.com/usedcars/details-824290-Maruti_Esteem_VXi"], "price": ["Rs. 1,10,000"], "transm": ["Petrol"], "kms": ["11,415 km "], "fuel": ["Petrol"], "owner": [], "model": ["Maruti Esteem VXi"], "color": ["Silver"]}
{"city": ["Ahmedabad"], "yom": ["2011"], "url": ["http://www.gaadi.com/usedcars/details-824289-Maruti_Swift+DZire_VDi"], "price": ["Rs. 5,00,000"], "transm": ["Diesel"], "kms": ["35,000 km "], "fuel": ["Diesel"], "owner": [], "model": ["Maruti Swift DZire VDi"], "color": ["Silver"]}
{"city": ["Aurangabad"], "yom": ["2009"], "url": ["http://www.gaadi.com/usedcars/details-824062-Tata_Safari_4X2+VX+DiCOR+2.2+V+T+T"], "price": ["Rs. 3,75,000"], "transm": ["Diesel"], "kms": ["1,00,000 km "], "fuel": ["Diesel"], "owner": [], "model": ["Tata Safari 4X2 VX DiCOR 2.2 V T T"], "color": ["Black"]}
{"city": ["Bangalore"], "yom": ["2011"], "url": ["http://www.gaadi.com/usedcars/details-824061-Ford_Figo_1.4+Duratorq+Titanium"], "price": ["Rs. 4,45,000"], "transm": ["Diesel"], "kms": ["55,344 km "], "fuel": ["Diesel"], "owner": [], "model": ["Ford Figo 1.4 Duratorq Titanium"], "color": ["Grey"]}
{"city": ["Kolkata"], "yom": ["2011"], "url": ["http://www.gaadi.com/usedcars/details-824231-Skoda_Laura_1.8+TSI+Active"], "price": ["Rs. 5,10,000"], "transm": ["Petrol"], "kms": ["35,000 km "], "fuel": ["Petrol"], "owner": [], "model": ["Skoda Laura 1.8 TSI Active"], "color": ["Black"]}
{"city": ["Mumbai"], "yom": ["2004"], "url": ["http://www.gaadi.com/usedcars/details-824230-Maruti_Versa_DX2"], "price": ["Rs. 1,15,000"], "transm": ["Petrol"], "kms": ["44,513 km "], "fuel": ["Petrol"], "owner": [], "model": ["Maruti Versa DX2"], "color": ["Black"]}
{"city": ["Indore"], "yom": ["2009"], "url": ["http://www.gaadi.com/usedcars/details-824951-Maruti_Omni_LPG+BS+III"], "price": ["Rs. 1,50,000"], "transm": ["Lpg"], "kms": ["50,000 km "], "fuel": ["Lpg"], "owner": [], "model": ["Maruti Omni LPG BS-III"], "color": ["Red"]}
{"city": ["Chennai"], "yom": ["2014"], "url": ["http://www.gaadi.com/usedcars/details-824949-Honda_Amaze_SX+MT+Diesel"], "price": ["Rs. 7,10,000"], "transm": ["Diesel"], "kms": ["11,000 km "], "fuel": ["Diesel"], "owner": [], "model": ["Honda Amaze SX MT Diesel"], "color": ["Blue"]}
{"city": ["Mumbai"], "yom": ["2011"], "url": ["http://www.gaadi.com/usedcars/details-823723-Maruti_Ritz_LXI"], "price": ["Rs. 3,35,000"], "transm": ["Petrol"], "kms": ["41,000 km "], "fuel": ["Petrol"], "owner": [], "model": ["Maruti Ritz LXI"], "color": ["Silky silver"]}
{"city": ["Nagpur"], "yom": ["2014"], "url": ["http://www.gaadi.com/usedcars/details-823722-Maruti_Alto+800_VXi"], "price": ["Rs. 3,60,000"], "transm": ["Petrol"], "kms": ["9,000 km "], "fuel": ["Petrol"], "owner": [], "model": ["Maruti Alto 800 VXi"], "color": ["Black"]}
{"city": ["Thane"], "yom": ["2013"], "url": ["http://www.gaadi.com/usedcars/details-824389-Maruti_Ertiga_LXi"], "price": ["Rs. 6,40,000"], "transm": ["Petrol"], "kms": ["33,940 km "], "fuel": ["Petrol"], "owner": [], "model": ["Maruti Ertiga LXi"], "color": ["Superior white"]}
{"city": [], "yom": ["2006"], "url": ["http://www.gaadi.com/usedcars/details-824388-Ford_Fiesta_Titanium+Diesel"], "price": ["Rs. 2,50,000"], "transm": ["Diesel"], "kms": ["97,500 km "], "fuel": ["Diesel"], "owner": [], "model": ["Ford Fiesta Titanium Diesel"], "color": ["White"]}
{"city": ["Chennai"], "yom": ["2012"], "url": ["http://www.gaadi.com/usedcars/details-823803-Ford_Figo_1.4+Duratorq+ZXI"], "price": ["Rs. 5,00,000"], "transm": ["Diesel"], "kms": ["4,000 km "], "fuel": ["Diesel"], "owner": [], "model": ["Ford Figo 1.4 Duratorq ZXI"], "color": ["Silver"]}
{"city": ["New Delhi"], "yom": ["2010"], "url": ["http://www.gaadi.com/usedcars/details-823799-Tata_Manza_Aura++%2B++Safire"], "price": ["Rs. 2,00,000"], "transm": ["Cng"], "kms": ["81,267 km "], "fuel": ["Cng"], "owner": [], "model": ["Tata Manza Aura (+) Safire"], "color": ["Silver"]}
{"city": ["Chennai"], "yom": ["2008"], "url": ["http://www.gaadi.com/usedcars/details-823752-Hyundai_i10_Magna+1.1"], "price": ["Rs. 2,10,000"], "transm": ["Petrol"], "kms": ["46,000 km "], "fuel": ["Petrol"], "owner": [], "model": ["Hyundai i10 Magna 1.1"], "color": ["Grey"]}
{"city": ["Ludhiana"], "yom": ["2013"], "url": ["http://www.gaadi.com/usedcars/details-823751-Honda_Brio_S+MT"], "price": ["Rs. 3,50,000"], "transm": ["Petrol"], "kms": ["35,000 km "], "fuel": ["Petrol"], "owner": [], "model": ["Honda Brio S MT"], "color": ["Tafeta white"]}
{"city": ["Bangalore"], "yom": ["2010"], "url": ["http://www.gaadi.com/usedcars/details-824288-Toyota_Innova_2.5+VX+7+Seater"], "price": ["Rs. 12,00,000"], "transm": ["Diesel"], "kms": ["41,314 km "], "fuel": ["Diesel"], "owner": [], "model": ["Toyota Innova 2.5 VX 7-Seater"], "color": ["Grey mica metallic"]}
{"city": ["Mysore"], "yom": ["2004"], "url": ["http://www.gaadi.com/usedcars/details-824287-Maruti_WagonR_Lxi"], "price": ["Rs. 1,70,000"], "transm": ["Petrol"], "kms": ["85,000 km "], "fuel": ["Petrol"], "owner": [], "model": ["Maruti WagonR Lxi"], "color": ["Yellow"]}
{"city": ["Raipur"], "yom": ["2007"], "url": ["http://www.gaadi.com/usedcars/details-824059-Maruti_Zen+Estilo_LXI"], "price": ["Rs. 1,65,000"], "transm": ["Petrol"], "kms": ["45,000 km "], "fuel": ["Petrol"], "owner": [], "model": ["Maruti Zen Estilo LXI"], "color": ["Red"]}
{"city": ["Mumbai"], "yom": ["2007"], "url": ["http://www.gaadi.com/usedcars/details-824058-Hyundai_i10_Era"], "price": ["Rs. 1,75,000"], "transm": ["Petrol"], "kms": ["37,000 km "], "fuel": ["Petrol"], "owner": [], "model": ["Hyundai i10 Era"], "color": ["Silky beige"]}
{"city": ["Mumbai"], "yom": ["2011"], "url": ["http://www.gaadi.com/usedcars/details-824229-Tata_Venture_EX"], "price": ["Rs. 2,20,000"], "transm": ["Diesel"], "kms": ["44,000 km "], "fuel": ["Diesel"], "owner": [], "model": ["Tata Venture EX"], "color": ["Meteor silver"]}
{"city": ["Aurangabad"], "yom": ["2010"], "url": ["http://www.gaadi.com/usedcars/details-824228-Maruti_Swift+DZire_VDi"], "price": ["Rs. 5,20,000"], "transm": ["Diesel"], "kms": ["1,11,000 km "], "fuel": ["Diesel"], "owner": [], "model": ["Maruti Swift DZire VDi"], "color": ["White"]}
{"city": ["Chennai"], "yom": ["2008"], "url": ["http://www.gaadi.com/usedcars/details-824948-Tata_Sumo+Victa_GX+TC+7+Str+BSIII"], "price": ["Rs. 4,85,000"], "transm": ["Diesel"], "kms": ["85,000 km "], "fuel": ["Diesel"], "owner": [], "model": ["Tata Sumo Victa GX TC 7 Str BSIII"], "color": ["Passion red"]}
{"city": ["Mumbai"], "yom": ["2003"], "url": ["http://www.gaadi.com/usedcars/details-824947-Hyundai_Santro_LP"], "price": ["Rs. 85,000"], "transm": ["Petrol"], "kms": ["1,10,713 km "], "fuel": ["Petrol"], "owner": [], "model": ["Hyundai Santro LP"], "color": ["Platinum"]}
{"city": ["New Delhi"], "yom": ["2007"], "url": ["http://www.gaadi.com/usedcars/details-823721-Maruti_Swift+2005+++2011_VXI"], "price": ["Rs. 2,50,000"], "transm": ["Petrol"], "kms": ["55,000 km "], "fuel": ["Petrol"], "owner": [], "model": ["Maruti Swift 2005 - 2011 VXI"], "color": ["Silver"]}
{"city": ["New Delhi"], "yom": ["2009"], "url": ["http://www.gaadi.com/usedcars/details-823720-Maruti_Swift+2005+++2011_LXi"], "price": ["Rs. 3,25,000"], "transm": ["Petrol"], "kms": ["80,000 km "], "fuel": ["Petrol"], "owner": [], "model": ["Maruti Swift 2005 - 2011 LXi"], "color": ["Red"]}
{"city": ["Nagpur"], "yom": ["2013"], "url": ["http://www.gaadi.com/usedcars/details-824387-Maruti_WagonR+2010+2012_VXI"], "price": ["Rs. 4,12,000"], "transm": ["Petrol"], "kms": ["25,000 km "], "fuel": ["Petrol"], "owner": [], "model": ["Maruti WagonR 2010-2012 VXI"], "color": ["Silver grey"]}
{"city": ["Nagpur"], "yom": ["2008"], "url": ["http://www.gaadi.com/usedcars/details-824386-Hyundai_Getz+Prime_1.3+GVS"], "price": ["Rs. 2,25,000"], "transm": ["Petrol"], "kms": ["68,000 km "], "fuel": ["Petrol"], "owner": [], "model": ["Hyundai Getz Prime 1.3 GVS"], "color": ["Silver"]}
{"city": ["Kolkata"], "yom": ["2010"], "url": ["http://www.gaadi.com/usedcars/details-823798-Tata_Manza_Aura++%2B++Safire"], "price": ["Rs. 2,25,000"], "transm": ["Petrol"], "kms": ["27,000 km "], "fuel": ["Petrol"], "owner": [], "model": ["Tata Manza Aura (+) Safire"], "color": ["White"]}
{"city": ["Amravati"], "yom": ["2011"], "url": ["http://www.gaadi.com/usedcars/details-823797-Toyota_Corolla+Altis_D+4D+J"], "price": ["Rs. 7,50,000"], "transm": ["Diesel"], "kms": ["1,22,500 km "], "fuel": ["Diesel"], "owner": [], "model": ["Toyota Corolla Altis D-4D J"], "color": ["White"]}
{"city": ["Ludhiana"], "yom": ["2003"], "url": ["http://www.gaadi.com/usedcars/details-823750-Hyundai_Santro_DX"], "price": ["Rs. 77,000"], "transm": ["Petrol"], "kms": ["55,000 km "], "fuel": ["Petrol"], "owner": [], "model": ["Hyundai Santro DX"], "color": ["Bright green"]}
{"city": ["Bangalore"], "yom": ["2010"], "url": ["http://www.gaadi.com/usedcars/details-823747-Chevrolet_Cruze+2009+2012_LTZ"], "price": ["Rs. 10,80,000"], "transm": ["Diesel"], "kms": ["57,597 km "], "fuel": ["Diesel"], "owner": [], "model": ["Chevrolet Cruze 2009-2012 LTZ"], "color": ["Summit white"]}
{"city": ["Mohali"], "yom": ["2011"], "url": ["http://www.gaadi.com/usedcars/details-824286-Ford_Figo_1.4+Duratorq+ZXI"], "price": ["Rs. 3,40,000"], "transm": ["Diesel"], "kms": ["63,000 km "], "fuel": ["Diesel"], "owner": [], "model": ["Ford Figo 1.4 Duratorq ZXI"], "color": ["Black"]}
{"city": ["Mumbai"], "yom": ["2006"], "url": ["http://www.gaadi.com/usedcars/details-824285-Toyota_Corolla_H3"], "price": ["Rs. 2,45,000"], "transm": ["Petrol"], "kms": ["93,904 km "], "fuel": ["Petrol"], "owner": [], "model": ["Toyota Corolla H3"], "color": ["Super white"]}
{"city": ["Mumbai"], "yom": ["2009"], "url": ["http://www.gaadi.com/usedcars/details-824057-Honda_City+2008++2011_1.5+V+MT"], "price": ["Rs. 3,50,000"], "transm": ["Petrol"], "kms": ["72,298 km "], "fuel": ["Petrol"], "owner": [], "model": ["Honda City 2008 -2011 1.5 V MT"], "color": ["Platinum"]}
{"city": ["Chennai"], "yom": ["2010"], "url": ["http://www.gaadi.com/usedcars/details-824056-Maruti_Ritz_LXI"], "price": ["Rs. 3,30,000"], "transm": ["Petrol"], "kms": ["54,000 km "], "fuel": ["Petrol"], "owner": [], "model": ["Maruti Ritz LXI"], "color": ["Black"]}
{"city": ["Aurangabad"], "yom": ["2009"], "url": ["http://www.gaadi.com/usedcars/details-824227-Tata_Indigo_XL+Grand+Dicor"], "price": ["Rs. 3,30,000"], "transm": ["Diesel"], "kms": ["79,000 km "], "fuel": ["Diesel"], "owner": [], "model": ["Tata Indigo XL Grand Dicor"], "color": ["Carbon black"]}
{"city": ["New Delhi"], "yom": ["2012"], "url": ["http://www.gaadi.com/usedcars/details-824226-Mercedes+Benz_C+Class+2009+2014_250+CDI+Elegance"], "price": ["Rs. 20,00,000"], "transm": ["Diesel"], "kms": ["55,000 km "], "fuel": ["Diesel"], "owner": [], "model": ["Mercedes Benz C Class 2009-2014 250 CDI Elegance"], "color": ["Grey"]}
{"city": ["Indore"], "yom": ["1999"], "url": ["http://www.gaadi.com/usedcars/details-824942-Maruti_Omni_8+Seater"], "price": ["Rs. 70,000"], "transm": ["Petrol"], "kms": ["42,000 km "], "fuel": ["Petrol"], "owner": [], "model": ["Maruti Omni 8 Seater"], "color": ["White"]}
{"city": ["Hyderabad"], "yom": ["2005"], "url": ["http://www.gaadi.com/usedcars/details-824939-Honda_Accord+2003+2008_2.4+VTI++L++AT+"], "price": ["Rs. 4,75,000"], "transm": ["Petrol"], "kms": ["69,614 km "], "fuel": ["Petrol"], "owner": [], "model": ["Honda Accord 2003-2008 2.4 VTI  L (AT)"], "color": ["Silver"]}
{"city": ["Trivandram"], "yom": ["2012"], "url": ["http://www.gaadi.com/usedcars/details-823719-Maruti_Alto+800_LXi"], "price": ["Rs. 2,40,000"], "transm": ["Petrol"], "kms": ["17,000 km "], "fuel": ["Petrol"], "owner": [], "model": ["Maruti Alto 800 LXi"], "color": ["Sky bkue"]}
{"city": ["Bhopal"], "yom": ["2012"], "url": ["http://www.gaadi.com/usedcars/details-823717-Maruti_Swift_ZDi"], "price": ["Rs. 5,50,000"], "transm": ["Diesel"], "kms": ["58,000 km "], "fuel": ["Diesel"], "owner": [], "model": ["Maruti Swift ZDi"], "color": ["Pearl arctict white"]}
{"city": ["Indore"], "yom": ["2012"], "url": ["http://www.gaadi.com/usedcars/details-823994-Hyundai_Verna+Fluidic_1.6+CRDI+SX"], "price": ["Rs. 7,71,000"], "transm": ["Diesel"], "kms": ["37,000 km "], "fuel": ["Diesel"], "owner": [], "model": ["Hyundai Verna Fluidic 1.6 CRDI SX"], "color": ["Silver"]}
{"city": ["Jaipur"], "yom": ["2013"], "url": ["http://www.gaadi.com/usedcars/details-824385-Volkswagen_Polo+2010+2014_1.2L+Trendline++Diesel+"], "price": ["Rs. 5,35,000"], "transm": ["Diesel"], "kms": ["32,072 km "], "fuel": ["Diesel"], "owner": [], "model": ["Volkswagen Polo 2010-2014 1.2L Trendline (Diesel)"], "color": ["White"]}
{"city": ["Cochin"], "yom": ["2014"], "url": ["http://www.gaadi.com/usedcars/details-824384-Maruti_Ertiga_VXi"], "price": ["Rs. 7,00,000"], "transm": ["Petrol"], "kms": ["18,000 km "], "fuel": ["Petrol"], "owner": [], "model": ["Maruti Ertiga VXi"], "color": ["White"]}
{"city": ["Hyderabad"], "yom": ["2012"], "url": ["http://www.gaadi.com/usedcars/details-823793-Maruti_WagonR_Lxi+CNG"], "price": ["Rs. 3,80,000"], "transm": ["Cng"], "kms": ["52,211 km "], "fuel": ["Cng"], "owner": [], "model": ["Maruti WagonR Lxi CNG"], "color": ["Grey"]}
{"city": ["Dehradun"], "yom": ["2014"], "url": ["http://www.gaadi.com/usedcars/details-823745-Chevrolet_Enjoy_1.3+LS+++8"], "price": ["Rs. 4,50,000"], "transm": ["Diesel"], "kms": ["47,000 km "], "fuel": ["Diesel"], "owner": [], "model": ["Chevrolet Enjoy 1.3 LS - 8"], "color": ["White"]}
{"city": ["Mumbai"], "yom": ["2008"], "url": ["http://www.gaadi.com/usedcars/details-824284-Tata_Indica+Vista+2008+++2011_Aqua+Quadrajet+BS+III"], "price": ["Rs. 1,90,000"], "transm": ["Diesel"], "kms": ["53,156 km "], "fuel": ["Diesel"], "owner": [], "model": ["Tata Indica Vista 2008 - 2011 Aqua Quadrajet BS-III"], "color": ["Blue"]}
{"city": ["Pune"], "yom": ["2003"], "url": ["http://www.gaadi.com/usedcars/details-824055-Hyundai_Santro+Xing_XS"], "price": ["Rs. 1,45,000"], "transm": ["Petrol"], "kms": ["35,000 km "], "fuel": ["Petrol"], "owner": [], "model": ["Hyundai Santro Xing XS"], "color": ["Passion red"]}
{"city": ["Chennai"], "yom": ["2009"], "url": ["http://www.gaadi.com/usedcars/details-824225-Maruti_A+Star_Vxi"], "price": ["Rs. 2,20,000"], "transm": ["Petrol"], "kms": ["57,500 km "], "fuel": ["Petrol"], "owner": [], "model": ["Maruti A Star Vxi"], "color": ["Grey"]}
{"city": ["Chennai"], "yom": ["2013"], "url": ["http://www.gaadi.com/usedcars/details-824938-Hyundai_Grand+i10_Magna+Diesel"], "price": ["Rs. 5,45,000"], "transm": ["Diesel"], "kms": ["13,000 km "], "fuel": ["Diesel"], "owner": [], "model": ["Hyundai Grand i10 Magna Diesel"], "color": ["Wine red - hyundai grand i10"]}
{"city": ["Bhopal"], "yom": ["2007"], "url": ["http://www.gaadi.com/usedcars/details-823716-Ford_Fiesta_Trend+Diesel"], "price": ["Rs. 2,30,000"], "transm": ["Diesel"], "kms": ["46,000 km "], "fuel": ["Diesel"], "owner": [], "model": ["Ford Fiesta Trend Diesel"], "color": ["Moondust silver"]}
{"city": ["Bangalore"], "yom": ["2007"], "url": ["http://www.gaadi.com/usedcars/details-823993-Hyundai_Santro+Xing_XE"], "price": ["Rs. 2,10,000"], "transm": ["Petrol"], "kms": ["71,000 km "], "fuel": ["Petrol"], "owner": [], "model": ["Hyundai Santro Xing XE"], "color": ["White"]}
{"city": ["Aurangabad"], "yom": ["2012"], "url": ["http://www.gaadi.com/usedcars/details-824383-Maruti_Swift_VDi"], "price": ["Rs. 5,50,000"], "transm": ["Diesel"], "kms": ["55,000 km "], "fuel": ["Diesel"], "owner": [], "model": ["Maruti Swift VDi"], "color": ["Pearl arctict white"]}
{"city": ["Cuttack"], "yom": ["2009"], "url": ["http://www.gaadi.com/usedcars/details-823791-Mahindra_Scorpio+2002+++2009_SLX"], "price": ["Rs. 5,00,000"], "transm": ["Diesel"], "kms": ["1,47,500 km "], "fuel": ["Diesel"], "owner": [], "model": ["Mahindra Scorpio 2002 - 2009 SLX"], "color": ["Brown"]}
{"city": ["Vapi"], "yom": ["1996"], "url": ["http://www.gaadi.com/usedcars/details-823744-Maruti_Gypsy_MG410W+ST"], "price": ["Rs. 3,30,000"], "transm": ["Petrol"], "kms": ["17,500 km "], "fuel": ["Petrol"], "owner": [], "model": ["Maruti Gypsy MG410W ST"], "color": ["White"]}
{"city": ["Mumbai"], "yom": ["2011"], "url": ["http://www.gaadi.com/usedcars/details-824283-Hyundai_Eon_Magna"], "price": ["Rs. 2,65,000"], "transm": ["Petrol"], "kms": ["26,000 km "], "fuel": ["Petrol"], "owner": [], "model": ["Hyundai Eon Magna"], "color": ["Pristine blue"]}
{"city": ["Raipur"], "yom": ["2010"], "url": ["http://www.gaadi.com/usedcars/details-824054-Maruti_Ritz_VXI"], "price": ["Rs. 3,50,000"], "transm": ["Petrol"], "kms": ["37,000 km "], "fuel": ["Petrol"], "owner": [], "model": ["Maruti Ritz VXI"], "color": ["Silver"]}
{"city": ["Faridabad"], "yom": ["2008"], "url": ["http://www.gaadi.com/usedcars/details-824224-Maruti_DZire+2012+2015_VXi"], "price": ["Rs. 3,00,000"], "transm": ["Petrol"], "kms": ["23,000 km "], "fuel": ["Petrol"], "owner": [], "model": ["Maruti DZire 2012-2015 VXi"], "color": ["Black"]}
{"city": ["Chennai"], "yom": ["2012"], "url": ["http://www.gaadi.com/usedcars/details-824937-Hyundai_Verna+Fluidic_1.6+CRDI+SX"], "price": ["Rs. 7,80,000"], "transm": ["Diesel"], "kms": ["33,000 km "], "fuel": ["Diesel"], "owner": [], "model": ["Hyundai Verna Fluidic 1.6 CRDI SX"], "color": ["Silver"]}
{"city": ["Bangalore"], "yom": ["2006"], "url": ["http://www.gaadi.com/usedcars/details-823713-Ford_Ikon_1.3+Flair"], "price": ["Rs. 1,89,000"], "transm": ["Petrol"], "kms": ["74,303 km "], "fuel": ["Petrol"], "owner": [], "model": ["Ford Ikon 1.3 Flair"], "color": ["Diamond white"]}
{"city": ["Bhopal"], "yom": ["2012"], "url": ["http://www.gaadi.com/usedcars/details-823992-Maruti_Eeco_7+Seater"], "price": ["Rs. 3,00,000"], "transm": ["Petrol"], "kms": ["10,000 km "], "fuel": ["Petrol"], "owner": [], "model": ["Maruti Eeco 7-Seater"], "color": ["Silky silver"]}
{"city": ["Aurangabad"], "yom": ["2009"], "url": ["http://www.gaadi.com/usedcars/details-824382-Skoda_Laura_Base"], "price": ["Rs. 7,00,000"], "transm": ["Diesel"], "kms": ["89,000 km "], "fuel": ["Diesel"], "owner": [], "model": ["Skoda Laura Base"], "color": ["Calla white"]}
{"city": ["Bangalore"], "yom": ["2011"], "url": ["http://www.gaadi.com/usedcars/details-823790-Audi_Q5_3.0+TDI"], "price": ["Rs. 39,00,000"], "transm": ["Diesel"], "kms": ["58,757 km "], "fuel": ["Diesel"], "owner": [], "model": ["Audi Q5 3.0 TDI"], "color": ["Q.grey"]}
{"city": ["Dehradun"], "yom": ["2014"], "url": ["http://www.gaadi.com/usedcars/details-823743-Maruti_WagonR_Vxi"], "price": ["Rs. 3,90,000"], "transm": ["Petrol"], "kms": ["9,000 km "], "fuel": ["Petrol"], "owner": [], "model": ["Maruti WagonR Vxi"], "color": ["Silky silver"]}
{"city": ["Mumbai"], "yom": ["2007"], "url": ["http://www.gaadi.com/usedcars/details-824282-Chevrolet_Aveo_1.4"], "price": ["Rs. 1,00,000"], "transm": ["Petrol"], "kms": ["54,000 km "], "fuel": ["Petrol"], "owner": [], "model": ["Chevrolet Aveo 1.4"], "color": ["Cashmeer"]}
{"city": ["Bangalore"], "yom": ["2009"], "url": ["http://www.gaadi.com/usedcars/details-824053-Hyundai_i10_Sportz+1.2"], "price": ["Rs. 3,50,000"], "transm": ["Petrol"], "kms": ["29,000 km "], "fuel": ["Petrol"], "owner": [], "model": ["Hyundai i10 Sportz 1.2"], "color": ["Golden"]}
{"city": ["Faridabad"], "yom": ["2014"], "url": ["http://www.gaadi.com/usedcars/details-824223-Maruti_Eeco_7+Seater"], "price": ["Rs. 3,80,000"], "transm": ["Petrol"], "kms": ["15,000 km "], "fuel": ["Petrol"], "owner": [], "model": ["Maruti Eeco 7-Seater"], "color": ["Silver"]}
{"city": ["Nagpur"], "yom": ["2009"], "url": ["http://www.gaadi.com/usedcars/details-824936-Hyundai_i10_Era"], "price": ["Rs. 2,80,000"], "transm": ["Petrol"], "kms": ["36,000 km "], "fuel": ["Petrol"], "owner": [], "model": ["Hyundai i10 Era"], "color": ["Sleek silver"]}
{"city": ["Bhopal"], "yom": ["2007"], "url": ["http://www.gaadi.com/usedcars/details-823712-Chevrolet_Optra+SRV_1.6"], "price": ["Rs. 2,80,000"], "transm": ["Petrol"], "kms": ["30,000 km "], "fuel": ["Petrol"], "owner": [], "model": ["Chevrolet Optra SRV 1.6"], "color": ["Cherry"]}
{"city": ["Bangalore"], "yom": ["2011"], "url": ["http://www.gaadi.com/usedcars/details-823989-Hyundai_i10_Sportz+1.2+AT"], "price": ["Rs. 4,50,000"], "transm": ["Petrol"], "kms": ["65,855 km "], "fuel": ["Petrol"], "owner": [], "model": ["Hyundai i10 Sportz 1.2 AT"], "color": ["Silver"]}
{"city": ["Chennai"], "yom": ["2002"], "url": ["http://www.gaadi.com/usedcars/details-824042-Mitsubishi_Lancer_1.5+CNX"], "price": ["Rs. 3,30,000"], "transm": ["Diesel"], "kms": ["1,05,000 km "], "fuel": ["Diesel"], "owner": [], "model": ["Mitsubishi Lancer 1.5 CNX"], "color": ["Warm silver"]}
{"city": ["Thane"], "yom": ["2012"], "url": ["http://www.gaadi.com/usedcars/details-823786-Maruti_Ertiga_VDi"], "price": ["Rs. 7,50,000"], "transm": ["Diesel"], "kms": ["38,763 km "], "fuel": ["Diesel"], "owner": [], "model": ["Maruti Ertiga VDi"], "color": ["Superior white"]}
{"city": ["Bangalore"], "yom": ["2009"], "url": ["http://www.gaadi.com/usedcars/details-823785-Honda_City_S+MT"], "price": ["Rs. 5,95,000"], "transm": ["Petrol"], "kms": ["59,593 km "], "fuel": ["Petrol"], "owner": [], "model": ["Honda City S MT"], "color": ["Black"]}
{"city": ["Dehradun"], "yom": ["2005"], "url": ["http://www.gaadi.com/usedcars/details-823742-Mahindra_Scorpio_S6+%2B"], "price": ["Rs. 3,35,000"], "transm": ["Diesel"], "kms": ["60,000 km "], "fuel": ["Diesel"], "owner": [], "model": ["Mahindra Scorpio S6 +"], "color": ["Molten red"]}
{"city": ["Dehradun"], "yom": ["2006"], "url": ["http://www.gaadi.com/usedcars/details-823741-Maruti_Alto+800_LX"], "price": ["Rs. 1,50,000"], "transm": ["Petrol"], "kms": ["40,000 km "], "fuel": ["Petrol"], "owner": [], "model": ["Maruti Alto 800 LX"], "color": ["Silky silver"]}
{"city": ["Mumbai"], "yom": ["2012"], "url": ["http://www.gaadi.com/usedcars/details-824281-Hyundai_Eon_Era"], "price": ["Rs. 2,55,000"], "transm": ["Petrol"], "kms": ["65,000 km "], "fuel": ["Petrol"], "owner": [], "model": ["Hyundai Eon Era"], "color": ["Coral white"]}
{"city": ["Mumbai"], "yom": ["2010"], "url": ["http://www.gaadi.com/usedcars/details-824280-Maruti_Alto_LXi"], "price": ["Rs. 1,98,000"], "transm": ["Petrol"], "kms": ["70,000 km "], "fuel": ["Petrol"], "owner": [], "model": ["Maruti Alto LXi"], "color": ["B. blaze"]}
{"city": ["Mumbai"], "yom": ["2009"], "url": ["http://www.gaadi.com/usedcars/details-824051-Fiat_Linea_Linea+Active"], "price": ["Rs. 2,45,000"], "transm": ["Petrol"], "kms": ["98,000 km "], "fuel": ["Petrol"], "owner": [], "model": ["Fiat Linea Linea Active"], "color": ["Minimal grey"]}
{"city": ["Hyderabad"], "yom": ["2011"], "url": ["http://www.gaadi.com/usedcars/details-824050-Honda_Civic+2006+2009_1.8+V+MT"], "price": ["Rs. 2,70,000"], "transm": ["Petrol"], "kms": ["42,000 km "], "fuel": ["Petrol"], "owner": [], "model": ["Honda Civic 2006-2009 1.8 V MT"], "color": ["Grey"]}
{"city": ["Amritsar"], "yom": ["2008"], "url": ["http://www.gaadi.com/usedcars/details-824222-Ford_Ikon_1.3+LXi+NXt"], "price": ["Rs. 80,000"], "transm": ["Petrol"], "kms": ["1,00,000 km "], "fuel": ["Petrol"], "owner": [], "model": ["Ford Ikon 1.3 LXi NXt"], "color": ["Panther black"]}
{"city": ["Kolkata"], "yom": ["2010"], "url": ["http://www.gaadi.com/usedcars/details-824221-Skoda_Superb+2009+++2014_1.8+TSI+AT"], "price": ["Rs. 7,80,000"], "transm": ["Petrol"], "kms": ["35,000 km "], "fuel": ["Petrol"], "owner": [], "model": ["Skoda Superb 2009 - 2014 1.8 TSI AT"], "color": ["Silver"]}
{"city": ["Nagpur"], "yom": ["2009"], "url": ["http://www.gaadi.com/usedcars/details-824935-Hyundai_i10_Era"], "price": ["Rs. 2,50,000"], "transm": ["Petrol"], "kms": ["40,000 km "], "fuel": ["Petrol"], "owner": [], "model": ["Hyundai i10 Era"], "color": ["Star dust"]}
{"city": ["Nagpur"], "yom": ["2000"], "url": ["http://www.gaadi.com/usedcars/details-824934-Hyundai_Santro_DX"], "price": ["Rs. 1,20,000"], "transm": ["Petrol"], "kms": ["68,741 km "], "fuel": ["Petrol"], "owner": [], "model": ["Hyundai Santro DX"], "color": ["Silver"]}
{"city": ["Bhopal"], "yom": ["2005"], "url": ["http://www.gaadi.com/usedcars/details-823711-Ford_Endeavour_2.5L+4x2"], "price": ["Rs. 5,50,000"], "transm": ["Diesel"], "kms": ["97,000 km "], "fuel": ["Diesel"], "owner": [], "model": ["Ford Endeavour 2.5L 4x2"], "color": ["Moondust silver"]}
{"city": ["Bhopal"], "yom": ["2008"], "url": ["http://www.gaadi.com/usedcars/details-823710-Chevrolet_Captiva_LTZ+AWD"], "price": ["Rs. 8,00,000"], "transm": ["Diesel"], "kms": ["62,000 km "], "fuel": ["Diesel"], "owner": [], "model": ["Chevrolet Captiva LTZ AWD"], "color": ["Black"]}
{"city": ["Gurgaon"], "yom": ["2011"], "url": ["http://www.gaadi.com/usedcars/details-823988-Hyundai_i20+2008+++2012_1.2+Magna"], "price": ["Rs. 3,50,000"], "transm": ["Petrol"], "kms": ["27,000 km "], "fuel": ["Petrol"], "owner": [], "model": ["Hyundai i20 2008 - 2012 1.2 Magna"], "color": ["Blue"]}
{"city": ["Indore"], "yom": ["2012"], "url": ["http://www.gaadi.com/usedcars/details-824041-Mahindra_Bolero_Plus"], "price": ["Rs. 5,50,000"], "transm": ["Diesel"], "kms": ["70,000 km "], "fuel": ["Diesel"], "owner": [], "model": ["Mahindra Bolero Plus"], "color": ["Grey"]}
{"city": ["Mumbai"], "yom": ["2006"], "url": ["http://www.gaadi.com/usedcars/details-824039-Ford_Endeavour_2.5L+4x2"], "price": ["Rs. 5,25,000"], "transm": ["Diesel"], "kms": ["1,02,247 km "], "fuel": ["Diesel"], "owner": [], "model": ["Ford Endeavour 2.5L 4x2"], "color": ["Black"]}
{"city": ["Chennai"], "yom": ["2011"], "url": ["http://www.gaadi.com/usedcars/details-823783-Mahindra_XUV500_W8+2WD"], "price": ["Rs. 10,25,000"], "transm": ["N/a"], "kms": ["67,500 km "], "fuel": ["N/a"], "owner": [], "model": ["Mahindra XUV500 W8 2WD"], "color": ["Silver"]}
{"city": ["Dehradun"], "yom": ["2008"], "url": ["http://www.gaadi.com/usedcars/details-823740-Skoda_Laura_L+n+K+AT"], "price": ["Rs. 5,15,000"], "transm": ["Diesel"], "kms": ["1,33,000 km "], "fuel": ["Diesel"], "owner": [], "model": ["Skoda Laura L n K AT"], "color": ["Candy white"]}
{"city": ["New Delhi"], "yom": ["2011"], "url": ["http://www.gaadi.com/usedcars/details-823738-Mitsubishi_Pajero_3.2+DI+D"], "price": ["Rs. 15,50,000"], "transm": ["Diesel"], "kms": ["50,000 km "], "fuel": ["Diesel"], "owner": [], "model": ["Mitsubishi Pajero 3.2 DI-D"], "color": ["Iceberg silver"]}
{"city": ["Ahmedabad"], "yom": ["2013"], "url": ["http://www.gaadi.com/usedcars/details-824278-Maruti_Swift+DZire_VDi"], "price": ["Rs. 6,15,000"], "transm": ["Diesel"], "kms": ["35,000 km "], "fuel": ["Diesel"], "owner": [], "model": ["Maruti Swift DZire VDi"], "color": ["White"]}
{"city": ["New Delhi"], "yom": ["2009"], "url": ["http://www.gaadi.com/usedcars/details-824277-Mercedes+Benz_C+Class+2009+2014_200+K+Elegance+AT"], "price": ["Rs. 11,00,000"], "transm": ["Petrol"], "kms": ["36,000 km "], "fuel": ["Petrol"], "owner": [], "model": ["Mercedes Benz C Class 2009-2014 200 K Elegance AT"], "color": ["Silver"]}
{"city": ["Hyderabad"], "yom": ["2013"], "url": ["http://www.gaadi.com/usedcars/details-824049-Chevrolet_Beat+2010+++2014_1.2+LT"], "price": ["Rs. 4,25,000"], "transm": ["Petrol"], "kms": ["31,000 km "], "fuel": ["Petrol"], "owner": [], "model": ["Chevrolet Beat 2010 - 2014 1.2 LT"], "color": ["Grey"]}
{"city": ["Chennai"], "yom": ["2010"], "url": ["http://www.gaadi.com/usedcars/details-824048-Maruti_Swift_ZXi"], "price": ["Rs. 4,10,000"], "transm": ["Petrol"], "kms": ["29,000 km "], "fuel": ["Petrol"], "owner": [], "model": ["Maruti Swift ZXi"], "color": ["White"]}
{"city": ["Kolkata"], "yom": ["2014"], "url": ["http://www.gaadi.com/usedcars/details-824220-Mahindra_XUV500_W8+AWD"], "price": ["Rs. 11,80,000"], "transm": ["Diesel"], "kms": ["29,000 km "], "fuel": ["Diesel"], "owner": [], "model": ["Mahindra XUV500 W8 AWD"], "color": ["Satin white"]}
{"city": ["Mumbai"], "yom": ["2007"], "url": ["http://www.gaadi.com/usedcars/details-824219-Maruti_SX4_VXI"], "price": ["Rs. 2,35,000"], "transm": ["Petrol"], "kms": ["1,05,772 km "], "fuel": ["Petrol"], "owner": [], "model": ["Maruti SX4 VXI"], "color": ["Pearl arctict white"]}
{"city": ["Nagpur"], "yom": ["2009"], "url": ["http://www.gaadi.com/usedcars/details-824933-Hyundai_Verna_1.6+i"], "price": ["Rs. 4,00,000"], "transm": ["Petrol"], "kms": ["42,687 km "], "fuel": ["Petrol"], "owner": [], "model": ["Hyundai Verna 1.6 i"], "color": ["White"]}
{"city": ["Lucknow"], "yom": ["2003"], "url": ["http://www.gaadi.com/usedcars/details-824932-Maruti_Esteem_VXi"], "price": ["Rs. 75,000"], "transm": ["Petrol"], "kms": ["65,000 km "], "fuel": ["Petrol"], "owner": [], "model": ["Maruti Esteem VXi"], "color": ["White"]}
{"city": ["Mumbai"], "yom": ["2011"], "url": ["http://www.gaadi.com/usedcars/details-823709-Tata_Manza_Aura+Quadrajet"], "price": ["Rs. 2,50,000"], "transm": ["Diesel"], "kms": ["81,238 km "], "fuel": ["Diesel"], "owner": [], "model": ["Tata Manza Aura Quadrajet"], "color": ["Grey"]}
{"city": ["Mumbai"], "yom": ["2007"], "url": ["http://www.gaadi.com/usedcars/details-823708-Maruti_Zen_Vx"], "price": ["Rs. 1,18,000"], "transm": ["Petrol"], "kms": ["55,435 km "], "fuel": ["Petrol"], "owner": [], "model": ["Maruti Zen Vx"], "color": ["Silver"]}
{"city": ["Gurgaon"], "yom": ["2009"], "url": ["http://www.gaadi.com/usedcars/details-823985-Mercedes+Benz_E+Class+2010+2013_280+CDI"], "price": ["Rs. 13,90,000"], "transm": ["Diesel"], "kms": ["67,000 km "], "fuel": ["Diesel"], "owner": [], "model": ["Mercedes Benz E Class 2010-2013 280 CDI"], "color": ["Black"]}
{"city": ["Gurgaon"], "yom": ["2004"], "url": ["http://www.gaadi.com/usedcars/details-823984-Toyota_Camry+2006+2012_M+T"], "price": ["Rs. 1,95,000"], "transm": ["Petrol"], "kms": ["95,000 km "], "fuel": ["Petrol"], "owner": [], "model": ["Toyota Camry 2006-2012 M/T"], "color": ["Black"]}
{"city": ["Pune"], "yom": ["2008"], "url": ["http://www.gaadi.com/usedcars/details-824038-Maruti_SX4_ZXI"], "price": ["Rs. 3,60,000"], "transm": ["Petrol"], "kms": ["60,000 km "], "fuel": ["Petrol"], "owner": [], "model": ["Maruti SX4 ZXI"], "color": ["Silky silver"]}
{"city": ["Chennai"], "yom": ["2012"], "url": ["http://www.gaadi.com/usedcars/details-824037-Mercedes+Benz_C+Class+2009+2014_250+CDI+Avantgrade"], "price": ["Rs. 25,00,000"], "transm": ["Diesel"], "kms": ["1,11,176 km "], "fuel": ["Diesel"], "owner": [], "model": ["Mercedes Benz C Class 2009-2014 250 CDI Avantgrade"], "color": ["Silver"]}
{"city": ["Bangalore"], "yom": ["2012"], "url": ["http://www.gaadi.com/usedcars/details-823735-Toyota_Fortuner+TRD+Sportivo_4X2+Automatic"], "price": ["Rs. 21,50,000"], "transm": ["Diesel"], "kms": ["29,707 km "], "fuel": ["Diesel"], "owner": [], "model": ["Toyota Fortuner TRD Sportivo 4X2 Automatic"], "color": ["Super white"]}
{"city": ["Dehradun"], "yom": ["2012"], "url": ["http://www.gaadi.com/usedcars/details-823733-Maruti_Alto+K10_VXi"], "price": ["Rs. 2,75,000"], "transm": ["Petrol"], "kms": ["28,000 km "], "fuel": ["Petrol"], "owner": [], "model": ["Maruti Alto K10 VXi"], "color": ["Silky silver"]}
{"city": ["Hyderabad"], "yom": ["2012"], "url": ["http://www.gaadi.com/usedcars/details-824276-Audi_A7_Sportback+3.0+TDI+quattro"], "price": ["Rs. 69,00,000"], "transm": ["Diesel"], "kms": ["30,000 km "], "fuel": ["Diesel"], "owner": [], "model": ["Audi A7 Sportback 3.0 TDI quattro"], "color": ["Ibis white"]}
{"city": ["Mohali"], "yom": ["2009"], "url": ["http://www.gaadi.com/usedcars/details-824275-Maruti_Alto_LX"], "price": ["Rs. 2,00,000"], "transm": ["Petrol"], "kms": ["33,000 km "], "fuel": ["Petrol"], "owner": [], "model": ["Maruti Alto LX"], "color": ["Silver"]}
{"city": ["Jodhpur"], "yom": ["2004"], "url": ["http://www.gaadi.com/usedcars/details-824047-Ford_Ikon_1.3+EXi"], "price": ["Rs. 75,001"], "transm": ["Petrol"], "kms": ["80,000 km "], "fuel": ["Petrol"], "owner": [], "model": ["Ford Ikon 1.3 EXi"], "color": ["Silver"]}
{"city": ["Jodhpur"], "yom": ["2010"], "url": ["http://www.gaadi.com/usedcars/details-824046-Maruti_Alto_Std"], "price": ["Rs. 1,40,001"], "transm": ["Petrol"], "kms": ["85,000 km "], "fuel": ["Petrol"], "owner": [], "model": ["Maruti Alto Std"], "color": ["White"]}
{"city": ["Aurangabad"], "yom": ["2012"], "url": ["http://www.gaadi.com/usedcars/details-824218-Tata_Nano_XM"], "price": ["Rs. 1,25,000"], "transm": ["Petrol"], "kms": ["27,000 km "], "fuel": ["Petrol"], "owner": [], "model": ["Tata Nano XM"], "color": ["Yellow"]}
{"city": ["Aurangabad"], "yom": ["2012"], "url": ["http://www.gaadi.com/usedcars/details-824217-Mahindra_Bolero_SLX"], "price": ["Rs. 6,25,000"], "transm": ["Diesel"], "kms": ["58,000 km "], "fuel": ["Diesel"], "owner": [], "model": ["Mahindra Bolero SLX"], "color": ["Diamond white"]}
{"city": ["Lucknow"], "yom": ["2003"], "url": ["http://www.gaadi.com/usedcars/details-824931-Maruti_800_Std"], "price": ["Rs. 60,000"], "transm": ["Petrol"], "kms": ["45,000 km "], "fuel": ["Petrol"], "owner": [], "model": ["Maruti 800 Std"], "color": ["White"]}
{"city": ["Lucknow"], "yom": ["2011"], "url": ["http://www.gaadi.com/usedcars/details-824930-Tata_Nano_LX"], "price": ["Rs. 95,000"], "transm": ["Petrol"], "kms": ["25,000 km "], "fuel": ["Petrol"], "owner": [], "model": ["Tata Nano LX"], "color": ["Meteor silver"]}
{"city": ["Allahabad"], "yom": ["2013"], "url": ["http://www.gaadi.com/usedcars/details-823706-Renault_Duster_110PS+RxZ+Plus"], "price": ["Rs. 9,00,000"], "transm": ["Diesel"], "kms": ["33,900 km "], "fuel": ["Diesel"], "owner": [], "model": ["Renault Duster 110PS RxZ Plus"], "color": ["Sienna"]}
{"city": ["Bangalore"], "yom": ["2013"], "url": ["http://www.gaadi.com/usedcars/details-823705-Honda_Jazz+2011+2013_X"], "price": ["Rs. 5,99,000"], "transm": ["Petrol"], "kms": ["36,763 km "], "fuel": ["Petrol"], "owner": [], "model": ["Honda Jazz 2011-2013 X"], "color": ["Grey"]}
{"city": ["Chennai"], "yom": ["2010"], "url": ["http://www.gaadi.com/usedcars/details-823983-Ford_Fiesta+2011+2014_Petrol"], "price": ["Rs. 3,90,000"], "transm": ["Petrol"], "kms": ["74,000 km "], "fuel": ["Petrol"], "owner": [], "model": ["Ford Fiesta 2011-2014 Petrol"], "color": ["Panther black"]}
{"city": ["Jaipur"], "yom": ["2012"], "url": ["http://www.gaadi.com/usedcars/details-823981-Mahindra_XUV500+2011+2015_W6"], "price": ["Rs. 11,50,000"], "transm": ["Diesel"], "kms": ["54,302 km "], "fuel": ["Diesel"], "owner": [], "model": ["Mahindra XUV500 2011-2015 W6"], "color": ["White"]}
{"city": ["Chennai"], "yom": ["2012"], "url": ["http://www.gaadi.com/usedcars/details-824036-Maruti_Wagon+R+1.0_VXI"], "price": ["Rs. 3,80,000"], "transm": ["Petrol"], "kms": ["9,000 km "], "fuel": ["Petrol"], "owner": [], "model": ["Maruti Wagon R 1.0 VXI"], "color": ["Sky blue"]}
{"city": ["Chennai"], "yom": ["2011"], "url": ["http://www.gaadi.com/usedcars/details-824035-Hyundai_i20_Sportz+Petrol"], "price": ["Rs. 4,20,000"], "transm": ["Petrol"], "kms": ["32,000 km "], "fuel": ["Petrol"], "owner": [], "model": ["Hyundai i20 Sportz Petrol"], "color": ["Black"]}
{"city": ["Dehradun"], "yom": ["2009"], "url": ["http://www.gaadi.com/usedcars/details-823732-Maruti_Swift_VDi"], "price": ["Rs. 3,40,000"], "transm": ["Diesel"], "kms": ["58,000 km "], "fuel": ["Diesel"], "owner": [], "model": ["Maruti Swift VDi"], "color": ["Pearl arctict white"]}
{"city": ["Mumbai"], "yom": ["2004"], "url": ["http://www.gaadi.com/usedcars/details-824274-Hyundai_Santro+Xing_GLS"], "price": ["Rs. 1,18,000"], "transm": ["Petrol"], "kms": ["11,659 km "], "fuel": ["Petrol"], "owner": [], "model": ["Hyundai Santro Xing GLS"], "color": ["Black"]}
{"city": ["Mumbai"], "yom": ["2004"], "url": ["http://www.gaadi.com/usedcars/details-824273-Hyundai_Santro+Xing_XG"], "price": ["Rs. 1,02,000"], "transm": ["Petrol"], "kms": ["83,446 km "], "fuel": ["Petrol"], "owner": [], "model": ["Hyundai Santro Xing XG"], "color": ["Platinum"]}
{"city": ["Karnal"], "yom": ["2010"], "url": ["http://www.gaadi.com/usedcars/details-824045-Tata_Safari_4X4+EXi+BS+III"], "price": ["Rs. 5,00,000"], "transm": ["Petrol"], "kms": ["71,000 km "], "fuel": ["Petrol"], "owner": [], "model": ["Tata Safari 4X4 EXi BS-III"], "color": ["White"]}
{"city": ["Coimbatore"], "yom": ["2012"], "url": ["http://www.gaadi.com/usedcars/details-824044-Ford_Figo_1.2+Duratec+Titanium"], "price": ["Rs. 4,25,000"], "transm": ["Petrol"], "kms": ["62,500 km "], "fuel": ["Petrol"], "owner": [], "model": ["Ford Figo 1.2 Duratec Titanium"], "color": ["Green"]}
{"city": ["Chennai"], "yom": ["2011"], "url": ["http://www.gaadi.com/usedcars/details-824043-Nissan_Micra+Active_XV"], "price": ["Rs. 4,00,000"], "transm": ["Petrol"], "kms": ["11,200 km "], "fuel": ["Petrol"], "owner": [], "model": ["Nissan Micra Active XV"], "color": ["Brick red"]}
{"city": ["Aurangabad"], "yom": ["2012"], "url": ["http://www.gaadi.com/usedcars/details-824216-Mahindra_Bolero_SLX"], "price": ["Rs. 6,25,000"], "transm": ["Diesel"], "kms": ["72,000 km "], "fuel": ["Diesel"], "owner": [], "model": ["Mahindra Bolero SLX"], "color": ["Diamond white"]}
{"city": ["New Delhi"], "yom": ["2012"], "url": ["http://www.gaadi.com/usedcars/details-824215-Volkswagen_Polo+2010+2014_1.2L+Trendline++Diesel+"], "price": ["Rs. 4,50,000"], "transm": ["Diesel"], "kms": ["68,000 km "], "fuel": ["Diesel"], "owner": [], "model": ["Volkswagen Polo 2010-2014 1.2L Trendline (Diesel)"], "color": ["White"]}
{"city": ["Gurgaon"], "yom": ["2008"], "url": ["http://www.gaadi.com/usedcars/details-824214-Mercedes+Benz_C+Class_C+200"], "price": ["Rs. 9,75,000"], "transm": ["Petrol"], "kms": ["61,029 km "], "fuel": ["Petrol"], "owner": [], "model": ["Mercedes Benz C Class C 200"], "color": ["White"]}
{"city": ["Lucknow"], "yom": ["2006"], "url": ["http://www.gaadi.com/usedcars/details-824929-Ford_Endeavour+2004+++2008_4X2+XLT"], "price": ["Rs. 5,00,000"], "transm": ["Diesel"], "kms": ["72,000 km "], "fuel": ["Diesel"], "owner": [], "model": ["Ford Endeavour 2004 - 2008 4X2 XLT"], "color": ["Black"]}
{"city": ["Lucknow"], "yom": ["2011"], "url": ["http://www.gaadi.com/usedcars/details-824928-Tata_Manza_Aura+Quadrajet"], "price": ["Rs. 3,60,000"], "transm": ["Diesel"], "kms": ["45,000 km "], "fuel": ["Diesel"], "owner": [], "model": ["Tata Manza Aura Quadrajet"], "color": ["White"]}
{"city": ["Lucknow"], "yom": ["2010"], "url": ["http://www.gaadi.com/usedcars/details-824927-Maruti_Alto_LXi"], "price": ["Rs. 1,70,000"], "transm": ["Petrol"], "kms": ["35,000 km "], "fuel": ["Petrol"], "owner": [], "model": ["Maruti Alto LXi"], "color": ["Silver"]}
{"city": ["Kottayam"], "yom": ["2013"], "url": ["http://www.gaadi.com/usedcars/details-823704-Maruti_DZire+2012+2015_VXi"], "price": ["Rs. 5,50,000"], "transm": ["Petrol"], "kms": ["16,000 km "], "fuel": ["Petrol"], "owner": [], "model": ["Maruti DZire 2012-2015 VXi"], "color": ["Grey"]}
{"city": ["Ahmedabad"], "yom": ["2013"], "url": ["http://www.gaadi.com/usedcars/details-823703-Maruti_Omni_8+Seater"], "price": ["Rs. 2,25,000"], "transm": ["Petrol"], "kms": ["39,000 km "], "fuel": ["Petrol"], "owner": [], "model": ["Maruti Omni 8 Seater"], "color": ["White"]}
{"city": ["Jodhpur"], "yom": ["2012"], "url": ["http://www.gaadi.com/usedcars/details-823702-Maruti_Alto_LXi"], "price": ["Rs. 2,20,000"], "transm": ["Petrol"], "kms": ["34,000 km "], "fuel": ["Petrol"], "owner": [], "model": ["Maruti Alto LXi"], "color": ["White"]}
{"city": ["Pune"], "yom": ["2012"], "url": ["http://www.gaadi.com/usedcars/details-823977-Maruti_Swift_LXi"], "price": ["Rs. 5,50,000"], "transm": ["Petrol"], "kms": ["72,500 km "], "fuel": ["Petrol"], "owner": [], "model": ["Maruti Swift LXi"], "color": ["Grey"]}
{"city": [], "yom": ["2012"], "url": ["http://www.gaadi.com/usedcars/details-823976-Skoda_Rapid+2011+2014_Elegance+1.6+TDI+CR+MT"], "price": ["Rs. 6,00,000"], "transm": ["Diesel"], "kms": ["1,02,500 km "], "fuel": ["Diesel"], "owner": [], "model": ["Skoda Rapid 2011-2014 Elegance 1.6 TDI CR MT"], "color": ["Other"]}
{"city": ["Mumbai"], "yom": ["2005"], "url": ["http://www.gaadi.com/usedcars/details-823972-Toyota_Corolla_H2+1.8+E"], "price": ["Rs. 2,50,000"], "transm": ["Petrol"], "kms": ["98,000 km "], "fuel": ["Petrol"], "owner": [], "model": ["Toyota Corolla H2 1.8 E"], "color": ["Silver metallic"]}
{"city": ["Cochin"], "yom": ["2011"], "url": ["http://www.gaadi.com/usedcars/details-824034-Maruti_WagonR+2010+2012_LXI"], "price": ["Rs. 3,50,000"], "transm": ["Petrol"], "kms": ["12,500 km "], "fuel": ["Petrol"], "owner": [], "model": ["Maruti WagonR 2010-2012 LXI"], "color": ["Medium blue"]}
{"city": ["Mumbai"], "yom": ["2010"], "url": ["http://www.gaadi.com/usedcars/details-824031-Toyota_Innova+2005+++2012_2.5+G+Diesel+8+seater"], "price": ["Rs. 8,35,000"], "transm": ["Diesel"], "kms": ["72,000 km "], "fuel": ["Diesel"], "owner": [], "model": ["Toyota Innova 2005 - 2012 2.5 G Diesel 8 seater"], "color": ["Grey mica metallic"]}
{"city": ["Kolkata"], "yom": ["2008"], "url": ["http://www.gaadi.com/usedcars/details-824213-Honda_CR+V+2007+2012_MT+W+Sun+Roof"], "price": ["Rs. 6,00,000"], "transm": ["Petrol"], "kms": ["42,000 km "], "fuel": ["Petrol"], "owner": [], "model": ["Honda CR-V 2007-2012 MT W/Sun Roof"], "color": ["Silver"]}
{"city": ["Mumbai"], "yom": ["2005"], "url": ["http://www.gaadi.com/usedcars/details-824212-Maruti_Swift_VXi"], "price": ["Rs. 1,85,000"], "transm": ["Petrol"], "kms": ["90,000 km "], "fuel": ["Petrol"], "owner": [], "model": ["Maruti Swift VXi"], "color": ["Blue"]}
{"city": ["Lucknow"], "yom": ["2009"], "url": ["http://www.gaadi.com/usedcars/details-824926-Fiat_Linea_Linea+Multi+Jet+Emotion"], "price": ["Rs. 3,50,000"], "transm": ["Diesel"], "kms": ["55,000 km "], "fuel": ["Diesel"], "owner": [], "model": ["Fiat Linea Linea Multi-Jet Emotion"], "color": ["Silver"]}
{"city": ["Mumbai"], "yom": ["2008"], "url": ["http://www.gaadi.com/usedcars/details-824925-Maruti_Wagon+R+Duo_LXI+LPG"], "price": ["Rs. 1,75,000"], "transm": ["Lpg"], "kms": ["30,147 km "], "fuel": ["Lpg"], "owner": [], "model": ["Maruti Wagon R Duo LXI LPG"], "color": ["Midnight black"]}
{"city": ["Bangalore"], "yom": ["2008"], "url": ["http://www.gaadi.com/usedcars/details-823701-Maruti_WagonR_Vxi"], "price": ["Rs. 2,40,000"], "transm": ["Petrol"], "kms": ["56,178 km "], "fuel": ["Petrol"], "owner": [], "model": ["Maruti WagonR Vxi"], "color": ["Black"]}
{"city": ["Ludhiana"], "yom": ["2010"], "url": ["http://www.gaadi.com/usedcars/details-823700-Maruti_Swift+2005+++2011_VDi"], "price": ["Rs. 4,25,000"], "transm": ["Diesel"], "kms": ["55,000 km "], "fuel": ["Diesel"], "owner": [], "model": ["Maruti Swift 2005 - 2011 VDi"], "color": ["White"]}
{"city": ["Lucknow"], "yom": ["2007"], "url": ["http://www.gaadi.com/usedcars/details-823970-Hyundai_Santro+Xing_GLS"], "price": ["Rs. 1,65,000"], "transm": ["Petrol"], "kms": ["55,000 km "], "fuel": ["Petrol"], "owner": [], "model": ["Hyundai Santro Xing GLS"], "color": ["Sleek silver"]}
{"city": ["Lucknow"], "yom": ["2006"], "url": ["http://www.gaadi.com/usedcars/details-823969-Maruti_Alto_LXi"], "price": ["Rs. 1,25,000"], "transm": ["Petrol"], "kms": ["65,000 km "], "fuel": ["Petrol"], "owner": [], "model": ["Maruti Alto LXi"], "color": ["Silver"]}
{"city": ["Pune"], "yom": ["2008"], "url": ["http://www.gaadi.com/usedcars/details-824030-Skoda_Laura_L+n+K+MT"], "price": ["Rs. 5,00,000"], "transm": ["Diesel"], "kms": ["90,000 km "], "fuel": ["Diesel"], "owner": [], "model": ["Skoda Laura L n K MT"], "color": ["Candy white"]}
{"city": ["Jamshedpur"], "yom": ["2011"], "url": ["http://www.gaadi.com/usedcars/details-824029-Hyundai_i10_Era"], "price": ["Rs. 2,75,000"], "transm": ["Petrol"], "kms": ["37,120 km "], "fuel": ["Petrol"], "owner": [], "model": ["Hyundai i10 Era"], "color": ["Pure white"]}
{"city": ["Aurangabad"], "yom": ["2011"], "url": ["http://www.gaadi.com/usedcars/details-824211-Mahindra_Scorpio+2010+2014_M2DI"], "price": ["Rs. 6,50,000"], "transm": ["Diesel"], "kms": ["70,000 km "], "fuel": ["Diesel"], "owner": [], "model": ["Mahindra Scorpio 2010-2014 M2DI"], "color": ["Black"]}
{"city": ["Mumbai"], "yom": ["2010"], "url": ["http://www.gaadi.com/usedcars/details-824924-Maruti_WagonR_Vxi"], "price": ["Rs. 3,50,000"], "transm": ["Petrol"], "kms": ["41,966 km "], "fuel": ["Petrol"], "owner": [], "model": ["Maruti WagonR Vxi"], "color": ["Superior white"]}
{"city": ["Mumbai"], "yom": ["2006"], "url": ["http://www.gaadi.com/usedcars/details-824923-Tata_Indigo_GLX"], "price": ["Rs. 98,000"], "transm": ["Petrol"], "kms": ["67,674 km "], "fuel": ["Petrol"], "owner": [], "model": ["Tata Indigo GLX"], "color": ["Arctic silver"]}
{"city": ["Mumbai"], "yom": ["2007"], "url": ["http://www.gaadi.com/usedcars/details-823699-Maruti_Zen+Estilo_VXI"], "price": ["Rs. 1,45,000"], "transm": ["Petrol"], "kms": ["1,04,982 km "], "fuel": ["Petrol"], "owner": [], "model": ["Maruti Zen Estilo VXI"], "color": ["Blue"]}
{"city": ["Amritsar"], "yom": ["2006"], "url": ["http://www.gaadi.com/usedcars/details-823695-Renault_Pulse_RxZ+Petrol"], "price": ["Rs. 2,00,000"], "transm": ["Petrol"], "kms": ["25,000 km "], "fuel": ["Petrol"], "owner": [], "model": ["Renault Pulse RxZ Petrol"], "color": ["Metallic  grey"]}
{"city": ["Lucknow"], "yom": ["2008"], "url": ["http://www.gaadi.com/usedcars/details-823968-Chevrolet_Tavera_LT+++L2+BS+II"], "price": ["Rs. 3,60,000"], "transm": ["Diesel"], "kms": ["70,000 km "], "fuel": ["Diesel"], "owner": [], "model": ["Chevrolet Tavera LT - L2 BS-II"], "color": ["Sterling silver"]}
{"city": ["Lucknow"], "yom": ["2006"], "url": ["http://www.gaadi.com/usedcars/details-823967-Mahindra_Scorpio+2010+2014_2.6+SLX+CRDe"], "price": ["Rs. 4,25,000"], "transm": ["Diesel"], "kms": ["80,000 km "], "fuel": ["Diesel"], "owner": [], "model": ["Mahindra Scorpio 2010-2014 2.6 SLX CRDe"], "color": ["Black"]}
{"city": ["New Delhi"], "yom": ["2004"], "url": ["http://www.gaadi.com/usedcars/details-824026-Maruti_WagonR_Lx"], "price": ["Rs. 1,00,000"], "transm": ["Petrol"], "kms": ["72,500 km "], "fuel": ["Petrol"], "owner": [], "model": ["Maruti WagonR Lx"], "color": ["Other"]}
{"city": ["New Delhi"], "yom": ["2011"], "url": ["http://www.gaadi.com/usedcars/details-824023-Honda_CR+V_2.4+L+4WD+AT+AVN"], "price": ["Rs. 12,50,000"], "transm": ["Petrol"], "kms": ["60,000 km "], "fuel": ["Petrol"], "owner": [], "model": ["Honda CR-V 2.4 L 4WD AT AVN"], "color": ["Silver"]}
{"city": ["Bangalore"], "yom": ["2013"], "url": ["http://www.gaadi.com/usedcars/details-824922-Mahindra_Scorpio+2010+2014_2.6"], "price": ["Rs. 11,00,000"], "transm": ["Diesel"], "kms": ["37,000 km "], "fuel": ["Diesel"], "owner": [], "model": ["Mahindra Scorpio 2010-2014 2.6"], "color": ["White"]}
{"city": ["Allahabad"], "yom": ["2010"], "url": ["http://www.gaadi.com/usedcars/details-823694-Chevrolet_Tavera_NEO+LT++L+7+seater+BS+III"], "price": ["Rs. 5,00,000"], "transm": ["Diesel"], "kms": ["73,456 km "], "fuel": ["Diesel"], "owner": [], "model": ["Chevrolet Tavera NEO LT- L 7 seater BS-III"], "color": ["Tan"]}
{"city": ["Allahabad"], "yom": ["2010"], "url": ["http://www.gaadi.com/usedcars/details-823693-Mahindra_Scorpio_S8"], "price": ["Rs. 6,95,000"], "transm": ["Diesel"], "kms": ["47,000 km "], "fuel": ["Diesel"], "owner": [], "model": ["Mahindra Scorpio S8"], "color": ["Fiery black"]}
{"city": ["Lucknow"], "yom": ["2009"], "url": ["http://www.gaadi.com/usedcars/details-823965-Mahindra_Scorpio+2010+2014_SLE+2.2+mHAWK"], "price": ["Rs. 5,25,000"], "transm": ["Diesel"], "kms": ["70,000 km "], "fuel": ["Diesel"], "owner": [], "model": ["Mahindra Scorpio 2010-2014 SLE 2.2 mHAWK"], "color": ["White"]}
{"city": ["New Delhi"], "yom": ["2008"], "url": ["http://www.gaadi.com/usedcars/details-823963-Maruti_WagonR_Lxi"], "price": ["Rs. 1,80,000"], "transm": ["Petrol"], "kms": ["71,589 km "], "fuel": ["Petrol"], "owner": [], "model": ["Maruti WagonR Lxi"], "color": ["Silky silver"]}
{"city": ["New Delhi"], "yom": ["2012"], "url": ["http://www.gaadi.com/usedcars/details-824020-Skoda_Rapid_1.5+TDI+CR+Ambition"], "price": ["Rs. 5,25,000"], "transm": ["Diesel"], "kms": ["60,000 km "], "fuel": ["Diesel"], "owner": [], "model": ["Skoda Rapid 1.5 TDI CR Ambition"], "color": ["Deep black pearl"]}
{"city": ["Kalyan-Dombivali"], "yom": ["2007"], "url": ["http://www.gaadi.com/usedcars/details-824018-Honda_City+ZX_GXi"], "price": ["Rs. 2,45,000"], "transm": ["Petrol"], "kms": ["57,500 km "], "fuel": ["Petrol"], "owner": [], "model": ["Honda City ZX GXi"], "color": ["Grey"]}
{"city": ["Allahabad"], "yom": ["2005"], "url": ["http://www.gaadi.com/usedcars/details-823692-Hyundai_Santro_LS"], "price": ["Rs. 1,75,000"], "transm": ["Petrol"], "kms": ["1,19,554 km "], "fuel": ["Petrol"], "owner": [], "model": ["Hyundai Santro LS"], "color": ["White"]}
{"city": ["Coimbatore"], "yom": ["2009"], "url": ["http://www.gaadi.com/usedcars/details-823962-Chevrolet_Spark_LS"], "price": ["Rs. 1,85,000"], "transm": ["Petrol"], "kms": ["82,500 km "], "fuel": ["Petrol"], "owner": [], "model": ["Chevrolet Spark LS"], "color": ["Other"]}
{"city": ["Pune"], "yom": ["2007"], "url": ["http://www.gaadi.com/usedcars/details-823959-Hyundai_Santro+Xing_XL"], "price": ["Rs. 1,75,000"], "transm": ["Petrol"], "kms": ["73,000 km "], "fuel": ["Petrol"], "owner": [], "model": ["Hyundai Santro Xing XL"], "color": ["Black"]}
{"city": ["Hyderabad"], "yom": ["2012"], "url": ["http://www.gaadi.com/usedcars/details-824017-Volkswagen_Vento+2010+2014_Highline+Diesel"], "price": ["Rs. 8,00,000"], "transm": ["Diesel"], "kms": ["6,000 km "], "fuel": ["Diesel"], "owner": [], "model": ["Volkswagen Vento 2010-2014 Highline Diesel"], "color": ["Blue"]}
{"city": ["Bhopal"], "yom": ["2012"], "url": ["http://www.gaadi.com/usedcars/details-824015-Tata_Vista_LS+Quadrajet"], "price": ["Rs. 3,00,000"], "transm": ["Diesel"], "kms": ["44,000 km "], "fuel": ["Diesel"], "owner": [], "model": ["Tata Vista LS Quadrajet"], "color": ["White"]}
{"city": ["Mohali"], "yom": ["2009"], "url": ["http://www.gaadi.com/usedcars/details-824108-Maruti_Alto_LXi"], "price": ["Rs. 2,05,000"], "transm": ["Petrol"], "kms": ["52,400 km "], "fuel": ["Petrol"], "owner": [], "model": ["Maruti Alto LXi"], "color": ["White"]}
{"city": ["New Delhi"], "yom": ["2003"], "url": ["http://www.gaadi.com/usedcars/details-823958-Hyundai_Accent_VIVA+ABS"], "price": ["Rs. 1,25,000"], "transm": ["Cng"], "kms": ["69,177 km "], "fuel": ["Cng"], "owner": [], "model": ["Hyundai Accent VIVA ABS"], "color": ["Silver"]}
{"city": ["New Delhi"], "yom": ["2012"], "url": ["http://www.gaadi.com/usedcars/details-823957-Hyundai_Verna+Fluidic_1.6+CRDI+SX"], "price": ["Rs. 7,00,000"], "transm": ["Diesel"], "kms": ["46,149 km "], "fuel": ["Diesel"], "owner": [], "model": ["Hyundai Verna Fluidic 1.6 CRDI SX"], "color": ["Silver"]}
{"city": ["Jamshedpur"], "yom": ["2012"], "url": ["http://www.gaadi.com/usedcars/details-824014-Hyundai_Eon_Magna"], "price": ["Rs. 2,85,000"], "transm": ["Petrol"], "kms": ["27,220 km "], "fuel": ["Petrol"], "owner": [], "model": ["Hyundai Eon Magna"], "color": ["Grey"]}
{"city": ["Rajkot"], "yom": ["2004"], "url": ["http://www.gaadi.com/usedcars/details-824012-Honda_City+2003+2005_1.5+Exi"], "price": ["Rs. 2,00,000"], "transm": ["Petrol"], "kms": ["1,42,500 km "], "fuel": ["Petrol"], "owner": [], "model": ["Honda City 2003-2005 1.5 Exi"], "color": ["Silver"]}
{"city": ["Mumbai"], "yom": ["2009"], "url": ["http://www.gaadi.com/usedcars/details-824107-Maruti_Swift_VDi"], "price": ["Rs. 3,75,000"], "transm": ["Diesel"], "kms": ["79,550 km "], "fuel": ["Diesel"], "owner": [], "model": ["Maruti Swift VDi"], "color": ["Silky silver"]}
{"city": ["Mumbai"], "yom": ["2010"], "url": ["http://www.gaadi.com/usedcars/details-824106-Maruti_Omni_Cargo"], "price": ["Rs. 1,00,000"], "transm": ["Petrol"], "kms": ["7,000 km "], "fuel": ["Petrol"], "owner": [], "model": ["Maruti Omni Cargo"], "color": ["White"]}
{"city": ["Kolkata"], "yom": ["2002"], "url": ["http://www.gaadi.com/usedcars/details-823955-Maruti_800_AC+BS+II"], "price": ["Rs. 80,000"], "transm": ["Petrol"], "kms": ["17,500 km "], "fuel": ["Petrol"], "owner": [], "model": ["Maruti 800 AC BS-II"], "color": ["Silver"]}
{"city": ["Hyderabad"], "yom": ["2012"], "url": ["http://www.gaadi.com/usedcars/details-823952-Volkswagen_Vento+2010+2014_Comfortline+Diesel"], "price": ["Rs. 7,60,000"], "transm": ["Diesel"], "kms": ["78,674 km "], "fuel": ["Diesel"], "owner": [], "model": ["Volkswagen Vento 2010-2014 Comfortline Diesel"], "color": ["Terra beige metallic"]}
{"city": ["Hyderabad"], "yom": ["2011"], "url": ["http://www.gaadi.com/usedcars/details-824011-Maruti_Alto+K10+2010+2014_LXi"], "price": ["Rs. 2,75,000"], "transm": ["Petrol"], "kms": ["10,800 km "], "fuel": ["Petrol"], "owner": [], "model": ["Maruti Alto K10 2010-2014 LXi"], "color": ["Red"]}
{"city": ["Hyderabad"], "yom": ["2010"], "url": ["http://www.gaadi.com/usedcars/details-824010-Ford_Figo+2010+2012_1.4+Duratorq+Diesel+Titanium"], "price": ["Rs. 3,75,000"], "transm": ["Diesel"], "kms": ["70,000 km "], "fuel": ["Diesel"], "owner": [], "model": ["Ford Figo 2010-2012 1.4 Duratorq Diesel Titanium"], "color": ["Silver"]}
{"city": ["Mumbai"], "yom": ["2008"], "url": ["http://www.gaadi.com/usedcars/details-824105-Mahindra+Renault_Logan+Edge_GLX"], "price": ["Rs. 1,50,000"], "transm": ["Petrol"], "kms": ["1,22,145 km "], "fuel": ["Petrol"], "owner": [], "model": ["Mahindra Renault Logan Edge GLX"], "color": ["Diamond white"]}
{"city": ["Hyderabad"], "yom": ["2012"], "url": ["http://www.gaadi.com/usedcars/details-823951-Renault_Duster+2012+++2015_1.5+RxZ"], "price": ["Rs. 9,50,000"], "transm": ["Diesel"], "kms": ["49,529 km "], "fuel": ["Diesel"], "owner": [], "model": ["Renault Duster 2012 - 2015 1.5 RxZ"], "color": ["White"]}
{"city": ["Mumbai"], "yom": ["2011"], "url": ["http://www.gaadi.com/usedcars/details-824006-Maruti_Swift+DZire_VDi"], "price": ["Rs. 4,85,000"], "transm": ["Diesel"], "kms": ["55,200 km "], "fuel": ["Diesel"], "owner": [], "model": ["Maruti Swift DZire VDi"], "color": ["Black"]}
{"city": ["Aurangabad"], "yom": ["2009"], "url": ["http://www.gaadi.com/usedcars/details-824104-Tata_Manza+Club+Class_VX"], "price": ["Rs. 3,50,000"], "transm": ["Diesel"], "kms": ["1,80,000 km "], "fuel": ["Diesel"], "owner": [], "model": ["Tata Manza Club Class VX"], "color": ["Jet silver"]}
{"city": ["Mumbai"], "yom": ["2009"], "url": ["http://www.gaadi.com/usedcars/details-823935-Maruti_Swift_VXi"], "price": ["Rs. 2,92,000"], "transm": ["Petrol"], "kms": ["49,500 km "], "fuel": ["Petrol"], "owner": [], "model": ["Maruti Swift VXi"], "color": ["Pearl arctict white"]}
{"city": ["Mumbai"], "yom": ["2009"], "url": ["http://www.gaadi.com/usedcars/details-824005-Toyota_Innova+2005+++2012_2.5+G4+7+SEATER"], "price": ["Rs. 7,75,000"], "transm": ["Diesel"], "kms": ["77,223 km "], "fuel": ["Diesel"], "owner": [], "model": ["Toyota Innova 2005 - 2012 2.5 G4 7 SEATER"], "color": ["Silver"]}
{"city": ["Chennai"], "yom": ["2013"], "url": ["http://www.gaadi.com/usedcars/details-824103-Maruti_Swift+DZire_ZDi"], "price": ["Rs. 6,90,000"], "transm": ["Diesel"], "kms": ["43,000 km "], "fuel": ["Diesel"], "owner": [], "model": ["Maruti Swift DZire ZDi"], "color": ["White"]}
{"city": ["Patna"], "yom": ["2010"], "url": ["http://www.gaadi.com/usedcars/details-823934-Mahindra_Scorpio_VLX+2.2+Mhawk+BS+III+Airbag"], "price": ["Rs. 7,00,000"], "transm": ["Diesel"], "kms": ["85,279 km "], "fuel": ["Diesel"], "owner": [], "model": ["Mahindra Scorpio VLX 2.2 Mhawk BS-III Airbag"], "color": ["Grey"]}
{"city": ["Gurgaon"], "yom": ["2008"], "url": ["http://www.gaadi.com/usedcars/details-824003-Porsche_Cayenne+2009+2014_S+V8+Tiptronic"], "price": ["Rs. 28,00,000"], "transm": ["Petrol"], "kms": ["80,000 km "], "fuel": ["Petrol"], "owner": [], "model": ["Porsche Cayenne 2009-2014 S V8 Tiptronic"], "color": ["Jet black metallic"]}
{"city": ["Mohali"], "yom": ["2015"], "url": ["http://www.gaadi.com/usedcars/details-824102-Hyundai_Grand+i10_Magna"], "price": ["Rs. 4,50,000"], "transm": ["Petrol"], "kms": ["2,000 km "], "fuel": ["Petrol"], "owner": [], "model": ["Hyundai Grand i10 Magna"], "color": ["White"]}
{"city": ["Nagpur"], "yom": ["2007"], "url": ["http://www.gaadi.com/usedcars/details-823933-Hyundai_Santro+Xing_XL+eRLX+Euro+III"], "price": ["Rs. 2,00,000"], "transm": ["Petrol"], "kms": ["55,523 km "], "fuel": ["Petrol"], "owner": [], "model": ["Hyundai Santro Xing XL eRLX Euro III"], "color": ["Silver"]}
{"city": ["Bhopal"], "yom": ["2015"], "url": ["http://www.gaadi.com/usedcars/details-824002-Tata_Safari_4X2+EX+DiCOR+BS+III"], "price": ["Rs. 11,20,000"], "transm": ["Diesel"], "kms": ["5,000 km "], "fuel": ["Diesel"], "owner": [], "model": ["Tata Safari 4X2 EX DiCOR BS-III"], "color": ["White"]}
{"city": ["Mumbai"], "yom": ["2007"], "url": ["http://www.gaadi.com/usedcars/details-824100-Mahindra+Renault_Logan+Edge_GLS"], "price": ["Rs. 1,38,000"], "transm": ["Petrol"], "kms": ["51,000 km "], "fuel": ["Petrol"], "owner": [], "model": ["Mahindra Renault Logan Edge GLS"], "color": ["Silver"]}
{"city": ["Nagpur"], "yom": ["2012"], "url": ["http://www.gaadi.com/usedcars/details-823931-Maruti_Zen+Estilo_2009+VXi+BS+IV"], "price": ["Rs. 3,15,000"], "transm": ["Petrol"], "kms": ["32,579 km "], "fuel": ["Petrol"], "owner": [], "model": ["Maruti Zen Estilo 2009 VXi BS-IV"], "color": ["White"]}
{"city": ["Gurgaon"], "yom": ["2010"], "url": ["http://www.gaadi.com/usedcars/details-824001-Mitsubishi_Pajero_2.8+SFX"], "price": ["Rs. 12,50,000"], "transm": ["Diesel"], "kms": ["47,000 km "], "fuel": ["Diesel"], "owner": [], "model": ["Mitsubishi Pajero 2.8 SFX"], "color": ["Pure black"]}
{"city": ["Gurgaon"], "yom": ["2013"], "url": ["http://www.gaadi.com/usedcars/details-824000-Mitsubishi_Pajero+Sport_4x4+MT"], "price": ["Rs. 19,75,000"], "transm": ["Diesel"], "kms": ["42,000 km "], "fuel": ["Diesel"], "owner": [], "model": ["Mitsubishi Pajero Sport 4x4 MT"], "color": ["Black"]}
{"city": ["Pune"], "yom": ["2011"], "url": ["http://www.gaadi.com/usedcars/details-824099-Maruti_Eeco_5+Seater+with+A+C%2BHeater"], "price": ["Rs. 2,70,000"], "transm": ["Petrol"], "kms": ["59,200 km "], "fuel": ["Petrol"], "owner": [], "model": ["Maruti Eeco 5-Seater with A/C+Heater"], "color": ["Superior white"]}
{"city": ["Mumbai"], "yom": ["2010"], "url": ["http://www.gaadi.com/usedcars/details-824098-Tata_Manza_Aura++ABS+"], "price": ["Rs. 2,00,000"], "transm": ["Diesel"], "kms": ["8,155 km "], "fuel": ["Diesel"], "owner": [], "model": ["Tata Manza Aura (ABS)"], "color": ["White"]}
{"city": ["New Delhi"], "yom": ["2011"], "url": ["http://www.gaadi.com/usedcars/details-823930-Toyota_Innova+2005+++2012_2.5+VX+7+SEATER+BS+IV"], "price": ["Rs. 10,99,000"], "transm": ["Diesel"], "kms": ["44,547 km "], "fuel": ["Diesel"], "owner": [], "model": ["Toyota Innova 2005 - 2012 2.5 VX 7 SEATER BS-IV"], "color": ["Champagne"]}
{"city": ["Gurgaon"], "yom": ["2011"], "url": ["http://www.gaadi.com/usedcars/details-823998-Honda_Jazz+2011+2013_X"], "price": ["Rs. 4,25,000"], "transm": ["Petrol"], "kms": ["40,000 km "], "fuel": ["Petrol"], "owner": [], "model": ["Honda Jazz 2011-2013 X"], "color": ["Burgundy"]}
{"city": ["Chennai"], "yom": ["2010"], "url": ["http://www.gaadi.com/usedcars/details-823996-Tata_Nano+2008+2013_LX"], "price": ["Rs. 1,05,000"], "transm": ["Petrol"], "kms": ["20,053 km "], "fuel": ["Petrol"], "owner": [], "model": ["Tata Nano 2008-2013 LX"], "color": ["Golden"]}
{"city": ["Pune"], "yom": ["2013"], "url": ["http://www.gaadi.com/usedcars/details-824097-Honda_CR+V_2.4+L+4WD+AT+AVN"], "price": ["Rs. 21,00,000"], "transm": ["Petrol"], "kms": ["25,000 km "], "fuel": ["Petrol"], "owner": [], "model": ["Honda CR-V 2.4 L 4WD AT AVN"], "color": ["White"]}
{"city": ["Chennai"], "yom": ["2009"], "url": ["http://www.gaadi.com/usedcars/details-823995-Hyundai_i20+2008+++2012_1.2+Magna"], "price": ["Rs. 3,50,000"], "transm": ["Petrol"], "kms": ["45,013 km "], "fuel": ["Petrol"], "owner": [], "model": ["Hyundai i20 2008 - 2012 1.2 Magna"], "color": ["White"]}
{"city": ["Aurangabad"], "yom": ["2012"], "url": ["http://www.gaadi.com/usedcars/details-824096-Chevrolet_Beat_PS+1.0"], "price": ["Rs. 3,30,000"], "transm": ["Diesel"], "kms": ["64,000 km "], "fuel": ["Diesel"], "owner": [], "model": ["Chevrolet Beat PS 1.0"], "color": ["Sand drift grey"]}
{"city": ["Karnal"], "yom": ["2010"], "url": ["http://www.gaadi.com/usedcars/details-824094-Maruti_Dzire+2008+++2012_VDI"], "price": ["Rs. 3,00,000"], "transm": ["Diesel"], "kms": ["1,04,000 km "], "fuel": ["Diesel"], "owner": [], "model": ["Maruti Dzire 2008 - 2012 VDI"], "color": ["White"]}
{"city": ["Karnal"], "yom": ["2007"], "url": ["http://www.gaadi.com/usedcars/details-824093-Hyundai_Verna+4S_1.4+Gamma+Base"], "price": ["Rs. 3,00,000"], "transm": ["Petrol"], "kms": ["1,35,000 km "], "fuel": ["Petrol"], "owner": [], "model": ["Hyundai Verna 4S 1.4 Gamma Base"], "color": ["Crystal white"]}
{"city": ["Karnal"], "yom": ["2005"], "url": ["http://www.gaadi.com/usedcars/details-824092-Hyundai_Elantra_SX"], "price": ["Rs. 2,25,000"], "transm": ["Petrol"], "kms": ["95,000 km "], "fuel": ["Petrol"], "owner": [], "model": ["Hyundai Elantra SX"], "color": ["White"]}
{"city": ["Mumbai"], "yom": ["2005"], "url": ["http://www.gaadi.com/usedcars/details-824091-Tata_Indigo_GLX"], "price": ["Rs. 95,000"], "transm": ["Petrol"], "kms": ["81,000 km "], "fuel": ["Petrol"], "owner": [], "model": ["Tata Indigo GLX"], "color": ["Aquatic blue"]}
{"city": ["Aurangabad"], "yom": ["2012"], "url": ["http://www.gaadi.com/usedcars/details-824090-Toyota_Innova_G+8+Seater++Petrol+"], "price": ["Rs. 12,50,000"], "transm": ["Petrol"], "kms": ["50,000 km "], "fuel": ["Petrol"], "owner": [], "model": ["Toyota Innova G 8-Seater (Petrol)"], "color": ["Silver mica metallic"]}
{"city": ["Aurangabad"], "yom": ["2011"], "url": ["http://www.gaadi.com/usedcars/details-824089-Hyundai_i20_Asta+1.2+Petrol"], "price": ["Rs. 4,45,000"], "transm": ["Petrol"], "kms": ["44,000 km "], "fuel": ["Petrol"], "owner": [], "model": ["Hyundai i20 Asta 1.2 Petrol"], "color": ["Silver"]}
{"city": ["Aurangabad"], "yom": ["2007"], "url": ["http://www.gaadi.com/usedcars/details-824088-Mahindra_Scorpio_S6+%2B"], "price": ["Rs. 2,89,000"], "transm": ["Diesel"], "kms": ["1,20,000 km "], "fuel": ["Diesel"], "owner": [], "model": ["Mahindra Scorpio S6 +"], "color": ["Mist silver"]}
{"city": ["Ahmedabad"], "yom": ["2011"], "url": ["http://www.gaadi.com/usedcars/details-824087-Mahindra_Verito_1.5+D4"], "price": ["Rs. 3,59,000"], "transm": ["Diesel"], "kms": ["44,538 km "], "fuel": ["Diesel"], "owner": [], "model": ["Mahindra Verito 1.5 D4"], "color": ["Mist silver"]}
{"city": ["Gurgaon"], "yom": ["2008"], "url": ["http://www.gaadi.com/usedcars/details-824085-Honda_City+ZX_GXi"], "price": ["Rs. 2,40,000"], "transm": ["Petrol"], "kms": ["70,000 km "], "fuel": ["Petrol"], "owner": [], "model": ["Honda City ZX GXi"], "color": ["Grey"]}
{"city": ["Hyderabad"], "yom": ["2012"], "url": ["http://www.gaadi.com/usedcars/details-824084-Nissan_Sunny+2011+2014_XV+Diesel"], "price": ["Rs. 7,25,000"], "transm": ["Diesel"], "kms": ["35,000 km "], "fuel": ["Diesel"], "owner": [], "model": ["Nissan Sunny 2011-2014 XV Diesel"], "color": ["White"]}
{"city": ["Gurgaon"], "yom": ["2010"], "url": ["http://www.gaadi.com/usedcars/details-824083-Toyota_Corolla+Altis+2011+++2014_1.8G"], "price": ["Rs. 6,25,000"], "transm": ["Petrol"], "kms": ["47,000 km "], "fuel": ["Petrol"], "owner": [], "model": ["Toyota Corolla Altis 2011 - 2014 1.8G"], "color": ["White"]}
{"city": ["Chennai"], "yom": ["2013"], "url": ["http://www.gaadi.com/usedcars/details-824082-Renault_Duster+2012+++2015_1.5+RxL+85+Plus"], "price": ["Rs. 8,00,000"], "transm": ["Diesel"], "kms": ["74,000 km "], "fuel": ["Diesel"], "owner": [], "model": ["Renault Duster 2012 - 2015 1.5 RxL 85 Plus"], "color": ["Brown"]}
{"city": ["Karnal"], "yom": ["2007"], "url": ["http://www.gaadi.com/usedcars/details-824081-Ford_Fiesta_Trend+Diesel"], "price": ["Rs. 2,00,000"], "transm": ["Diesel"], "kms": ["80,000 km "], "fuel": ["Diesel"], "owner": [], "model": ["Ford Fiesta Trend Diesel"], "color": ["Diamond white"]}
{"city": ["Karnal"], "yom": ["2006"], "url": ["http://www.gaadi.com/usedcars/details-824080-Toyota_Innova_2.0+VX+7+Seater++Petrol+"], "price": ["Rs. 4,80,000"], "transm": ["Petrol"], "kms": ["1,55,000 km "], "fuel": ["Petrol"], "owner": [], "model": ["Toyota Innova 2.0 VX 7-Seater (Petrol)"], "color": ["Super white"]}
{"city": ["Ahmedabad"], "yom": ["2012"], "url": ["http://www.gaadi.com/usedcars/details-824079-MINI_Cooper+2012+2014_1.6+Convertible"], "price": ["Rs. 36,00,000"], "transm": ["Petrol"], "kms": ["25,154 km "], "fuel": ["Petrol"], "owner": [], "model": ["MINI Cooper 2012-2014 1.6 Convertible"], "color": ["Bright green"]}
{"city": ["Mumbai"], "yom": ["2008"], "url": ["http://www.gaadi.com/usedcars/details-824078-Tata_Indigo+eCS_GLS"], "price": ["Rs. 1,35,000"], "transm": ["Petrol"], "kms": ["53,000 km "], "fuel": ["Petrol"], "owner": [], "model": ["Tata Indigo eCS GLS"], "color": ["Blue"]}
{"city": ["Mumbai"], "yom": ["2009"], "url": ["http://www.gaadi.com/usedcars/details-824077-Tata_Indica+Vista+2008+++2011_Aura+1.2+Safire"], "price": ["Rs. 1,48,000"], "transm": ["Petrol"], "kms": ["47,000 km "], "fuel": ["Petrol"], "owner": [], "model": ["Tata Indica Vista 2008 - 2011 Aura 1.2 Safire"], "color": ["Gold"]}
{"city": ["Mumbai"], "yom": ["2008"], "url": ["http://www.gaadi.com/usedcars/details-824076-Tata_Indica+Vista+2008+++2011_Aura+1.2+Safire"], "price": ["Rs. 1,90,000"], "transm": ["Petrol"], "kms": ["53,000 km "], "fuel": ["Petrol"], "owner": [], "model": ["Tata Indica Vista 2008 - 2011 Aura 1.2 Safire"], "color": ["Blue"]}
